Workbook
Name DemoCode: 'A3 Exercise'!$B$139
Name DemoDrop: 'B1 Exercise'!$B$156
Name DemoPeople: 'A3 Exercise'!$B$192
Name Exer1: 'B1 Exercise'!$B$14
Name Exer1: 'A3 Exercise'!$B$13
Name Exer2: 'B1 Exercise'!$B$37
Name Exer2: 'A3 Exercise'!$B$37
Name Exer3: 'B1 Exercise'!$B$59
Name Exer3: 'A3 Exercise'!$B$62
Name Exer4: 'B1 Exercise'!$B$103
Name Exer4: 'A3 Exercise'!$B$87
Name Exer5: 'B1 Exercise'!$B$138
Name Exer5: 'A3 Exercise'!$B$112
Name HowTo: 'B1 Instructions'!$B$24
Name HowTo: 'B1 Instructions'!$B$24
Name HowTo: 'A3 Instructions'!$B$25
Name ImportantNotes: 'B1 Instructions'!$B$78
Name ImportantNotes: 'B1 Instructions'!$B$78
Name ImportantNotes: 'A3 Instructions'!$B$53
Name mult: 'B1 Instructions'!$B$118
Name OneCol: 'A4 Instructions'!$B$36
Name OneCol: #REF!
Name Prerequesite: 'B1 Instructions'!$B$66
Name Prerequesite: 'B1 Instructions'!$B$66
Name Prerequesite: 'A3 Instructions'!$B$46
Name Reset: 'A4 Instructions'!#REF!
Name Reset: #REF!
Name ResetEx: 'A4 Instructions'!$B$65
Name ThePoint: 'B1 Instructions'!$B$3
Name ThePoint: 'B1 Instructions'!$B$3
Name ThePoint: 'A3 Instructions'!#REF!
Name Top: 'B1 Instructions'!$B$2
Name Top: 'B1 Instructions'!$B$2
Name Top: 'A3 Instructions'!#REF!
Name TopExercise: 'B1 Exercise'!$B$3
Name TopExercise: 'A3 Exercise'!$B$3
Name TwoCol: 'A4 Instructions'!$B$23
Name TwoCol: #REF!
Name Versus: 'B1 Instructions'!$B$130
Name wildcards: 'B1 Instructions'!$B$81

Sheet Excel Magic
E2: Dazzle with Data Using Excel Magic!
E3: Created by Julie Marcoux, Dalhousie University
E6: JUMP TO MAIN MENU
E9: CONTACT INFORMATION
E10: Last updated June 9, 2026
E12: This file is shared under CC BY-NC 4.0

Sheet Menu
E1: Return to Dazzling Title Screen
E3: Welcome to a workshop in which you will be amazed with Excel magic tricks.
E4: But don't worry, most of the tricks will be revealed!
E5: You too can become an Excel expert!
E7: SECTION A - Let's start with easy tricks that only require clicking around
C8: A1 | E8: You guys know about "paste as values" already, right? Everyone?
E9: "Go to special" time! We're going to color all empty cells in the worksheet! | G9: A2
C10: A3 | E10: We'll be done with "Flash fill" in a flash!
E11: We'll build a list of unique values by eliminating duplicates. | G11: A4
C12: A5 | E12: We're going to learn about my favorite Find/Replace tricks.
E15: SECTION B - Let's have fun with some formulas!
C16: B1 | E16: Let's take a look at XLOOKUP!
E17: Did you think we were going to forget about OR and AND? As IF! | G17: B2
C18: B3 | E18: We're going to COUNT from A to Z!
E19: We'll use our list of unique values and SumIf and SumIfs to do some magic! | G19: B4
E22: SECTION C - It's… too much! Have a look at some leftover features and formulas!
C23: C1 | E23: Let's concentrate on concatenation
E24: We'll take a quick look at LEFT, MID, RIGHT, and FIND. | G24: C2
C25: C3 | E25: Let's take a look at VLOOKUP!
E26: We're going to witness the power of CSE formulas. | G26: C4
E29: Need More Help?

Sheet A1 Instructions
A1: * | B1: Main Menu | C1: Exercise | D1: Data worksheet
C3: A1 PASTE AS VALUES
C5: What are we doing here?
C6: I'm making extra sure you know about Paste Special.
C7: It is SUCH a useful thing to know.
C8: I mostly use it to transform formulas into data.
C10: This is amazing! What if I want to do more?
C11: I guess you could explore the different options in the 'Paste Special' menu?
C13: How do I get started again?
C14: The example is ready to go, just keep reading!
C15: If you need a reset, copy-paste from the bottom of this worksheet
C16: Use the "Paste as values" button for copy-pasting as data.
A19: * | B19: INSTRUCTIONS
B20: Select cells containing formulas and copy them using your favorite method.
B21: Then click on the arrow under "Paste" in the "Home" ribbon and select one of the options as appropriate.
B23: If you don't quite understand what happens below in the example, reinitialize it by copy pasting the data and formulas at the bottom of the spreadsheet.
B24: Click on C32 and look at the formula bar. Copy paste C32 to C37 in the worksheet and see what happens. C32 and C37 should be different.
B25: Click on C32 again and copy it. In the "Clipboard" section of the "Home" ribbon, click on the dropdown arrow under "Paste".
B26: Without moving, select the first option under "Paste values".
B27: Click on C32 again and look at the formula bar. Copy-paste C32 to C37 and see what happens. C32 and C37 should be identical.
B29: Alternatively, go to the "Formulas" ribbon and click on "Show Formulas" in the "Formula Auditing" section.
A31: * | B31: Data | C31: Steps | Formulas
B32: I'm using | C32: =B32&" "&B33&". " &B34&" "&B35 -> I'm using concatenation. Let's transform that into values.
B33: concatenation | C33: =B36&" "&B37 -> Try copying in place and pasting as values.
B34: Let's transform that | C34: =B38&" "&B39&" "&B40&" "&B41&" "&B42 -> See what happens when you copy-paste from the formulas column before and after doing the paste as values.
B35: into values.
B36: Try copying in place
B37: and pasting as values.
B38: See what happens when
B39: you copy-paste
B40: from the formulas column
B41: before and after
B42: doing the paste as values.
A45: * | B45: RESET EXAMPLE
B47: I'm using | C47: =B47&" "&B48&". " &B49&" "&B50 -> I'm using concatenation. Let's transform that into values.
B48: concatenation | C48: =B51&" "&B52 -> Try copying in place and pasting as values.
B49: Let's transform that | C49: =B53&" "&B54&" "&B55&" "&B56&" "&B57 -> See what happens when you copy-paste from the formulas column before and after doing the paste as values.
B50: into values.
B51: Try copying in place
B52: and pasting as values.
B53: See what happens when
B54: you copy-paste
B55: from the formulas column
B56: before and after
B57: doing the paste as values.
B59: Select cells B47 to C57. Copy
B60: Click on cell B32. Paste (using whatever method you usually use to paste content).

Sheet A1 Exercise
A1: * | B1: Main Menu | C1: Instructions | D1: Data worksheet
A3: * | B3: PASTE AS VALUES EXERCISE
B4: OH NO! Someone has directly referenced data from the 2021 CSD worksheet in this worksheet.
B5: This displeases you, for some reason. Perhaps you are afraid of what will happen if you decide to delete the data worksheet?
B6: You are right to be afraid, if ANYTHING happens to 2021 CSD, then this entire worksheet stops working.
B8: For extra security, you decide to transform all the formulas in this worksheet as values, except for the 15+ population total.
B9: Start by previewing formulas by clicking on "Show Formulas" in the "Formula Auditing" section of the "Formulas" ribbon
B10: then turn off "Show Formulas". Transform the formulas in the table into values, skipping the formula that sums up the population total.
B11: You can check your work by clicking on "Show Formulas" in the "Formula Auditing" section of the "Formulas" ribbon.
A13: * | B13: Table to copy-paste as value | G13: Did it work?
B14: ='2021 CSD'!A1 -> Province | C14: ='2021 CSD'!D1 -> SUBDIV Name | D14: ='2021 CSD'!E1 -> Tot Pop 2021 | E14: Prov - County - TotPop | G14: Was the formula removed?
B15: ='2021 CSD'!A2 -> 12 | C15: ='2021 CSD'!D2 -> Barrington | D15: ='2021 CSD'!E2 -> 6523 | E15: ="NS-"&C15&"-"&D15 -> NS-Barrington-6523 | G15: =IF(OR(_xlfn.ISFORMULA(B15),_xlfn.ISFORMULA(C15),_xlfn.ISFORMULA(D15),_xlfn.ISFORMULA(E15)),"Try again","YAY!") -> Try again | H15: <-You want formulas on this row of the table removed
B16: ='2021 CSD'!A3 -> 12 | C16: ='2021 CSD'!D3 -> Clark's Harbour | D16: ='2021 CSD'!E3 -> 725 | E16: ="NS-"&C16&"-"&D16 -> NS-Clark's Harbour-725 | G16: =IF(OR(_xlfn.ISFORMULA(B16),_xlfn.ISFORMULA(C16),_xlfn.ISFORMULA(D16),_xlfn.ISFORMULA(E16)),"Try again","YAY!") -> Try again | H16: <-You want formulas on this row of the table removed
B17: ='2021 CSD'!A4 -> 12 | C17: ='2021 CSD'!D4 -> Shelburne | D17: ='2021 CSD'!E4 -> 4336 | E17: ="NS-"&C17&"-"&D17 -> NS-Shelburne-4336 | G17: =IF(OR(_xlfn.ISFORMULA(B17),_xlfn.ISFORMULA(C17),_xlfn.ISFORMULA(D17),_xlfn.ISFORMULA(E17)),"Try again","YAY!") -> Try again | H17: <-You want formulas on this row of the table removed
B18: ='2021 CSD'!A5 -> 12 | C18: ='2021 CSD'!D5 -> Shelburne | D18: ='2021 CSD'!E5 -> 1644 | E18: ="NS-"&C18&"-"&D18 -> NS-Shelburne-1644 | G18: =IF(OR(_xlfn.ISFORMULA(B18),_xlfn.ISFORMULA(C18),_xlfn.ISFORMULA(D18),_xlfn.ISFORMULA(E18)),"Try again","YAY!") -> Try again | H18: <-You want formulas on this row of the table removed
B19: ='2021 CSD'!A6 -> 12 | C19: ='2021 CSD'!D6 -> Lockeport | D19: ='2021 CSD'!E6 -> 476 | E19: ="NS-"&C19&"-"&D19 -> NS-Lockeport-476 | G19: =IF(OR(_xlfn.ISFORMULA(B19),_xlfn.ISFORMULA(C19),_xlfn.ISFORMULA(D19),_xlfn.ISFORMULA(E19)),"Try again","YAY!") -> Try again | H19: <-You want formulas on this row of the table removed
B20: ='2021 CSD'!A7 -> 12 | C20: ='2021 CSD'!D7 -> Argyle | D20: ='2021 CSD'!E7 -> 7870 | E20: ="NS-"&C20&"-"&D20 -> NS-Argyle-7870 | G20: =IF(OR(_xlfn.ISFORMULA(B20),_xlfn.ISFORMULA(C20),_xlfn.ISFORMULA(D20),_xlfn.ISFORMULA(E20)),"Try again","YAY!") -> Try again | H20: <-You want formulas on this row of the table removed
B21: ='2021 CSD'!A8 -> 12 | C21: ='2021 CSD'!D8 -> Yarmouth | D21: ='2021 CSD'!E8 -> 10067 | E21: ="NS-"&C21&"-"&D21 -> NS-Yarmouth-10067 | G21: =IF(OR(_xlfn.ISFORMULA(B21),_xlfn.ISFORMULA(C21),_xlfn.ISFORMULA(D21),_xlfn.ISFORMULA(E21)),"Try again","YAY!") -> Try again | H21: <-You want formulas on this row of the table removed
B22: ='2021 CSD'!A9 -> 12 | C22: ='2021 CSD'!D9 -> Yarmouth | D22: ='2021 CSD'!E9 -> 6829 | E22: ="NS-"&C22&"-"&D22 -> NS-Yarmouth-6829 | G22: =IF(OR(_xlfn.ISFORMULA(B22),_xlfn.ISFORMULA(C22),_xlfn.ISFORMULA(D22),_xlfn.ISFORMULA(E22)),"Try again","YAY!") -> Try again | H22: <-You want formulas on this row of the table removed
B23: ='2021 CSD'!A10 -> 12 | C23: ='2021 CSD'!D10 -> Yarmouth 33 | D23: ='2021 CSD'!E10 -> 181 | E23: ="NS-"&C23&"-"&D23 -> NS-Yarmouth 33-181 | G23: =IF(OR(_xlfn.ISFORMULA(B23),_xlfn.ISFORMULA(C23),_xlfn.ISFORMULA(D23),_xlfn.ISFORMULA(E23)),"Try again","YAY!") -> Try again | H23: <-You want formulas on this row of the table removed
B24: ='2021 CSD'!A11 -> 12 | C24: ='2021 CSD'!D11 -> Clare | D24: ='2021 CSD'!E11 -> 7678 | E24: ="NS-"&C24&"-"&D24 -> NS-Clare-7678 | G24: =IF(OR(_xlfn.ISFORMULA(B24),_xlfn.ISFORMULA(C24),_xlfn.ISFORMULA(D24),_xlfn.ISFORMULA(E24)),"Try again","YAY!") -> Try again | H24: <-You want formulas on this row of the table removed
B25: ='2021 CSD'!A12 -> 12 | C25: ='2021 CSD'!D12 -> Digby | D25: ='2021 CSD'!E12 -> 7242 | E25: ="NS-"&C25&"-"&D25 -> NS-Digby-7242 | G25: =IF(OR(_xlfn.ISFORMULA(B25),_xlfn.ISFORMULA(C25),_xlfn.ISFORMULA(D25),_xlfn.ISFORMULA(E25)),"Try again","YAY!") -> Try again | H25: <-You want formulas on this row of the table removed
B26: ='2021 CSD'!A13 -> 12 | C26: ='2021 CSD'!D13 -> Digby | D26: ='2021 CSD'!E13 -> 2001 | E26: ="NS-"&C26&"-"&D26 -> NS-Digby-2001 | G26: =IF(OR(_xlfn.ISFORMULA(B26),_xlfn.ISFORMULA(C26),_xlfn.ISFORMULA(D26),_xlfn.ISFORMULA(E26)),"Try again","YAY!") -> Try again | H26: <-You want formulas on this row of the table removed
B27: ='2021 CSD'!A14 -> 12 | C27: ='2021 CSD'!D14 -> Bear River (Part) 6 | D27: ='2021 CSD'!E14 -> 141 | E27: ="NS-"&C27&"-"&D27 -> NS-Bear River (Part) 6-141 | G27: =IF(OR(_xlfn.ISFORMULA(B27),_xlfn.ISFORMULA(C27),_xlfn.ISFORMULA(D27),_xlfn.ISFORMULA(E27)),"Try again","YAY!") -> Try again | H27: <-You want formulas on this row of the table removed
C28: Total population: | D28: =SUM(D15:D27) -> 55713 | G28: =IF(_xlfn.ISFORMULA(D28),"YAY!","Oh no!") -> YAY! | H28: <-You want to keep the formula on this row of the table

Sheet A2 Instructions
A1: * | B1: Main Menu | C1: Exercise
C3: A2 SELECT WITH CRITERIA
C5: What are we doing here?
C6: You're going to love this. It's simple and easy to do.
C7: We're simply going to select cells according to certain criteria,
C8: by using Excel's very own menus!
C10: The most useful applications I've found is getting to formulas quickly
C11: (yes, I know about displaying formulas instead of results in the formula menu),
C12: and finding empty cells.
C14: This is amazing! What if I want to do more?
C15: There are other ways of doing the same thing.
C16: You can do cool stuff with macros of course,
C17: and also by being really good at using find/replace…
... C22: Once you think you understand, go do the most fun exercise!
A25: * | B25: INSTRUCTIONS
B26: Either select a range of cells in which to search, or just don't do anything special to search the entire worksheet.
B27: Go to "Find & Select" in the "Editing" section of the "Home" ribbon and click on "Go To Special". Alternatively, press F5. Click on "Special".
B29: You will be able to select cells according to a specific criteria. Select a criteria and click on "Ok".
B30: Use "Enter" to quickly go from one cell to another.
B31: When cells are all selected like that, you can also apply some formatting to all cells at once if you'd like to do so.
B32: When you're finished, just click anywhere on the worksheet to un-select the cells. See? I wasn't kidding, this is really easy!
B34: In my example, we're selecting all empty cells in range E38 to G43, and then formatting them a bit differently to reveal the hidden smiley face!
A36: * | B36: Selecting blank cells example - Draw a happy face :)
B37: Select cells E41 to I46. Go to Home - Editing section - Find & Select - Go to Special.
B38: Click on "Blanks" and then "Ok". Use the fill tool in the font section of the home ribbon
B39: to apply a background color.
E41: 1 | F41: 2 | G41: 3 | H41: 4 | I41: 5
E42: 6 | G42: 8 | I42: 10
E43: 11 | F43: 12 | G43: 13 | H43: 14 | I43: 15
F44: 17 | G44: 18 | H44: 19
E45: 21 | I45: 25
E46: 26 | F46: 27 | G46: 28 | H46: 29 | I46: 30
A48: * | B48: RESET EXAMPLE
B50: Select cells E50 to I55. Copy. | E50: 1 | F50: 2 | G50: 3 | H50: 4 | I50: 5
B51: Click on cell E41. Paste. | E51: 6 | G51: 8 | I51: 10
E52: 11 | F52: 12 | G52: 13 | H52: 14 | I52: 15
F53: 17 | G53: 18 | H53: 19
E54: 21 | I54: 25
E55: 26 | F55: 27 | G55: 28 | H55: 29 | I55: 30

Sheet A2 Exercise
A3: * | B3: SELECT WITH CRITERIA EXERCISE
B4: Find all the cells with formulas in rows 8 to 14. Practice navigating from one formula to another, and then apply formatting to make the cells with
B5: Formulas pop out. You want the hidden message to be revealed even when the cells are no longer selected.
A7: * | B7: Formulas are hidden below
B8: ="*" -> * | C8: ="*" -> * | D8: ="*" -> * | E8: * | F8: ="*" -> * | G8: * | H8: * | I8: * | J8: ="*" -> * | K8: * | L8: ="*" -> * | M8: ="*" -> * | N8: ="*" -> * | O8: * | P8: ="*" -> * | Q8: ="*" -> * | R8: ="*" -> * | S8: * | T8: ="*" -> * | U8: ="*" -> * | V8: ="*" -> * | W8: * | X8: ="*" -> * | Y8: ="*" -> * | Z8: ="*" -> * | AA8: * | AB8: ="*" -> * | AC8: * | AD8: ="*" -> * | AE8: * | AF8: ="*" -> * | AG8: *
B9: ="*" -> * | C9: * | D9: * | E9: * | F9: * | G9: ="*" -> * | H9: * | I9: ="*" -> * | J9: * | K9: * | L9: ="*" -> * | M9: * | N9: ="*" -> * | O9: * | P9: ="*" -> * | Q9: * | R9: * | S9: * | T9: ="*" -> * | U9: * | V9: ="*" -> * | W9: * | X9: * | Y9: ="*" -> * | Z9: * | AA9: * | AB9: ="*" -> * | AC9: * | AD9: ="*" -> * | AE9: * | AF9: ="*" -> * | AG9: *
B10: ="*" -> * | C10: ="*" -> * | D10: ="*" -> * | E10: * | F10: * | G10: * | H10: ="*" -> * | I10: * | J10: * | K10: * | L10: ="*" -> * | M10: ="*" -> * | N10: ="*" -> * | O10: * | P10: ="*" -> * | Q10: ="*" -> * | R10: ="*" -> * | S10: * | T10: ="*" -> * | U10: ="*" -> * | V10: * | W10: * | X10: * | Y10: ="*" -> * | Z10: * | AA10: * | AB10: ="*" -> * | AC10: * | AD10: ="*" -> * | AE10: * | AF10: ="*" -> * | AG10: *
B11: ="*" -> * | C11: * | D11: * | E11: * | F11: * | G11: ="*" -> * | H11: * | I11: ="*" -> * | J11: * | K11: * | L11: ="*" -> * | M11: * | N11: * | O11: * | P11: ="*" -> * | Q11: * | R11: * | S11: * | T11: ="*" -> * | U11: * | V11: ="*" -> * | W11: * | X11: * | Y11: ="*" -> * | Z11: * | AA11: * | AB11: * | AC11: * | AD11: * | AE11: * | AF11: * | AG11: *
B12: ="*" -> * | C12: ="*" -> * | D12: ="*" -> * | E12: * | F12: ="*" -> * | G12: * | H12: * | I12: * | J12: ="*" -> * | K12: * | L12: ="*" -> * | M12: * | N12: * | O12: * | P12: ="*" -> * | Q12: ="*" -> * | R12: ="*" -> * | S12: * | T12: ="*" -> * | U12: * | V12: * | W12: ="*" -> * | X12: * | Y12: ="*" -> * | Z12: * | AA12: * | AB12: ="*" -> * | AC12: * | AD12: ="*" -> * | AE12: * | AF12: ="*" -> * | AG12: *
B13: * | C13: * | D13: * | E13: * | F13: * | G13: * | H13: * | I13: * | J13: * | K13: * | L13: * | M13: * | N13: * | O13: * | P13: * | Q13: * | R13: * | S13: * | T13: * | U13: * | V13: * | W13: * | X13: * | Y13: * | Z13: * | AA13: * | AB13: * | AC13: * | AD13: * | AE13: * | AF13: * | AG13: *
B14: * | C14: * | D14: * | E14: * | F14: * | G14: * | H14: * | I14: * | J14: * | K14: * | L14: * | M14: * | N14: * | O14: * | P14: * | Q14: * | R14: * | S14: * | T14: * | U14: * | V14: * | W14: * | X14: * | Y14: * | Z14: * | AA14: * | AB14: * | AC14: * | AD14: * | AE14: * | AF14: * | AG14: *

Sheet A3 Instructions
B3: A3 FLASH FILL
B5: What are we doing here?
B6: We're going to use Excel features to magically pull apart or put together text that has a pattern.
B7: You could use flash fill to extract first names from columns containing full names.
B8: You could also use it to combine multiple columns together while ignoring blank cells.
B10: This is amazing! What if I want to do more?
B11: Just keep practicing on your data! It only takes a second to try using flash fill.
B12: You may also want to look into formulas that work with text, such as in sections C1 and C2
B14: How do I get started again?
B15: Just keep reading to learn more about Flash Fill.
B16: Once you feel ready, go do the exercises!
A19: * | B19: Page Menu
B20: Scroll down after selecting item in menu - desired instructions are at the bottom of the screen
B21: How to get Flash Fill to work
B22: What needs to be in place for Flash Fill to work
B23: Important Flash Fill notes
A25: * | B25: INSTRUCTIONS | F25: Top
B26: Review the conditions that need to be in place for Flash Fill to work. | C26: Review here!
B27: Identify a column from which you need to extract data in a pattern, or columns with data that you want to concatenate. [1]
B28: Navigate to the first available blank column next to your data or insert a new blank column. Give your column an exciting title. [2]
B29: Move to the first (top) blank cell in your new blank column. [3]
B30: Manually enter the part of the pattern that you what you want to extract / input. Repeat with the next row. [3]
A32: * | B32: Method 1
B33: Select both rows with content in your "blank" column. [1]
B34: Double-click on the bottom-right of the selection. [2]
B35: Click on the "Auto Fill Options" icon that temporarily appears. [3]
B36: Select "Flash Fill" [4]
A38: * | B38: Method 2
B39: Select the last row in your "blank" column that has content.
B40: Press Ctrl-E on the keyboard (possibly Command-E on the Mac).
A42: * | B42: Both methods
B43: After a few columns, Excel might guess what you're doing and just automatically flash fill the column for you!
B44: If Flash Fill has incorrectly guessed the pattern, or if you have a complex pattern, try manually overwriting incorrect rows with the correct value in a cell or two before working on something else. Flash fill should magically adjust the rest of the column.
A46: * | B46: WHAT NEEDS TO BE IN PLACE FOR FLASH FILL TO WORK | F46: Top
B47: Flash fill only works in Excel 2016+.
B48: Flash fill will fill cells down and/or up a column, not across rows
B49: Your data needs to be organized in a table-like structure, preferably with headers/titles for your columns.
B50: Avoid having completely blank rows. Flash fill should still work if there are some blank cells in a column as long as other cells in the same row have content and no blank needs to go in the column you want to flash fill.
B51: There must be some sort of pattern to your data, a rule that can be used to extract/input the data that is logical and consistent.
A53: * | B53: SUPPLEMENTARY INFORMATION | F53: Top
B54: Flash fill is not dynamic. If you change content in your original column, your new column won't update itself. Use formulas instead of flash fill, or reapply flash fill.
B55: If using the Ctrl-E method, you can fill in the pattern at one of the easiest to fill in spots in your column. When you do Ctrl E, the column should fill down and up.
B56: Some problems are too complex for Flash Fill, in which case you'll need to consider alternatives.

Sheet A3 Exercise
C1: Main Menu | D1: Instructions | T1: Cells in this column and beyond are used for conditional formatting purposes and should be ignored. | AR1: Names | AS1: First Names | AT1: Last names | AU1: Adjective
A3: * | B3: Flash Fill Exercises | AR3: Arden "Awesome" Kayzak
AR4: Sara "Stupendous" Tumpane
A5: * | B5: Page Menu | AR5: Alex "Amazing" Cooper
B6: Scroll down after selecting item in menu - desired instructions are at the bottom of the screen | AR6: Sandra "Superb" Sawchuk
B7: Exercise 1: Random Famous People | AR7: Margaret "Marvelous" Vail
B8: Exercise 2: Random Famous People with Exceptions | AR8: Emanuela "Excellent" Chiriac
B9: Exercise 3: Busy busy airports! | AR9: Giovanna "Great" Badia
B10: Exercise 4: Don't call these numbers! | AR10: Vivek "Valuable" Jadon
B11: Exercise 5: Time travel with months | AR11: Chantal "Clever" Ripp
B12: Demo: Fun with codes
B13: Demo: People and comments
AR14: Amy "Astounding" Paterson
A15: * | B15: Exercise 1: Random Famous People | F15: Top | AR15: Tara "Talented" Stieglitz
AR16: Caleb "Creative" Domsy
B17: Instructions
B18: Use Flash Fill to extract the first name, last name, and adjectives in the random list of famous people.
B20: Example result
B21: Random Famous People | C21: First Name | D21: Last Name | E21: Adjective
B22: Avril 'Awesome' Lavigne | C22: Avril | D22: Lavigne | E22: Awesome
B24: Exercise table
B26: Random Famous People | C26: First Name | D26: Last Name | E26: Adjective | T26: First Name | U26: Last Name | V26: Adjective
B27: Avril 'Awesome' Lavigne | U27: Avril | V27: Lavigne | W27: Awesome
B28: Bryan 'Beautiful' Adams | U28: Bryan | V28: Adams | W28: Beautiful
B29: Celine 'Courageous' Dion | U29: Celine | V29: Dion | W29: Courageous
B30: Leonard 'Lovely' Cohen | U30: Leonard | V30: Cohen | W30: Lovely
B31: Michael 'Magical' Cera | U31: Michael | V31: Cera | W31: Magical
B32: Nathan 'Nice' Filion | U32: Nathan | V32: Filion | W32: Nice
B33: Nelly 'Notable' Furtado | U33: Nelly | V33: Furtado | W33: Notable
B34: Ryan 'Radiant' Gosling | U34: Ryan | V34: Gosling | W34: Radiant
B35: Santa 'Jolly' Claus | U35: Santa | V35: Claus | W35: Jolly
B36: Sarah 'Sensational' MacLachlan | U36: Sarah | V36: MacLachlan | W36: Sensational
B37: Willam 'Winner' Shatner | U37: Willam | V37: Shatner | W37: Winner
A39: * | B39: Exercise 2: Random Famous People with Exceptions | F39: Top
B41: Instructions
B42: Use Flash Fill to extract the adjective and last name, when some famous people don't have an adjective
B44: Example result
B45: Random Famous People | C45: Adj + Last Name
B46: Avril 'Awesome' Lavigne | C46: Awesome Lavigne
B47: Bryan Adams | C47: Adams
B49: Exercise table
B51: Random Famous People | C51: Adj + Last Name | U51: Last Name - Adjective
B52: Avril 'Awesome' Lavigne | U52: Awesome Lavigne
B53: Bryan Adams | U53: Adams
B54: Celine Dion | U54: Dion
B55: Leonard Cohen | U55: Cohen
B56: Michael 'Magical' Cera | U56: Magical Cera
B57: Nathan 'Nice' Filion | U57: Nice Filion
B58: Nelly 'Notable' Furtado | U58: Notable Furtado
B59: Ryan 'Radiant' Gosling | U59: Radiant Gosling
B60: Santa Claus | U60: Claus
B61: Sarah MacLachlan | U61: MacLachlan
B62: Willam 'Winner' Shatner | U62: Winner Shatner
A64: * | B64: Exercise 3: Busy busy airports! | F64: Top
B66: Instructions
B67: Use Flash Fill to put together busy airport names, add the word "airport" and add the IATA code in parentheses.
B69: Example result
B70: Airport Names | C70: IATIA Codes | D70: Airport Names + Airport + (IATA)
B71: Hartsfield-Jackson Atlanta | C71: ATL | D71: Hartsfield-Jackson Atlanta Airport (ATL)
B72: Dallas Fort Worth | C72: DFW | D72: Dallas Fort Worth Airport (DFW)
B74: Exercise table
B76: Airport Names | C76: IATIA Codes | D76: Airport Names + Airport + (IATA) | U76: Last Name - Adjective
B77: Hartsfield-Jackson Atlanta | C77: ATL | T77: Hartsfield-Jackson Atlanta Airport (ATL)
B78: Dallas Forth Worth | C78: DFW | T78: Dallas Forth Worth Airport (DFW)
B79: Denver | C79: DEN | T79: Denver Airport (DEN)
B80: O'Hare | C80: ORD | T80: O'Hare Airport (ORD)
B81: Dubai | C81: DXB | T81: Dubai Airport (DXB)
B82: Los Angeles | C82: LAX | T82: Los Angeles Airport (LAX)
B83: Istanbul | C83: IST | T83: Istanbul Airport (IST)
B84: Heathrow | C84: LHR | T84: Heathrow Airport (LHR)
B85: Indira Gandhi | C85: DEL | T85: Indira Gandhi Airport (DEL)
B86: Charles de Gaulle | C86: CDG | T86: Charles de Gaulle Airport (CDG)
B87: Halifax Standfield | C87: YHZ | T87: Halifax Standfield Airport (YHZ)
A89: * | B89: Exercise 4: Don't call these numbers! | F89: Top
B91: Instructions
B92: Use Flash Fill to reformat the phone numbers (in a ###-###-#### style), and to strip the area code.
B94: Example result
B95: Phone number | C95: Reformatted | D95: Area code removed
B96: (347) 777-9311 | C96: 347-777-9311 | D96: 777-9311
B97: (516) 234-0234 | C97: 516-234-0234 | D97: 234-0234
B99: Exercise table
B101: Phone numbers | C101: Reformatted | D101: Area code removed
B102: (347) 777-9311 | T102: 347-777-9311 | U102: 777-9311
B103: (516) 234-0234 | T103: 516-234-0234 | U103: 234-0234
B104: (613) 555-0001 | T104: 613-555-0001 | U104: 555-0001
B105: (613) 555-0179 | T105: 613-555-0179 | U105: 555-0179
B106: (613) 555-2368 | T106: 613-555-2368 | U106: 555-2368
B107: (613) 634-5789 | T107: 613-634-5789 | U107: 634-5789
B108: (902) 555-0113 | T108: 902-555-0113 | U108: 555-0113
B109: (902) 555-0123 | T109: 902-555-0123 | U109: 555-0123
B110: (902) 555-2368 | T110: 902-555-2368 | U110: 555-2368
B111: (902) 776-2323 | T111: 902-776-2323 | U111: 776-2323
B112: (916) 225-5887 | T112: 916-225-5887 | U112: 225-5887
A114: * | B114: Exercise 5: Time travel with months | F114: Top
B116: Instructions
B117: Use Flash Fill to extract the month abbreviations from this list of dates.
B118: You'll notice this isn't quite as efficient as using the TEXT formula…
B119: Dates taken from https://thecanadaguide.com/data/important-dates/
B121: Example result
B122: Date | C122: Historical Event | D122: Month | E122: Magical Text Formula
...

Sheet A4 Instructions
A1: * | B1: Main Menu | C1: Exercise | D1: Data worksheet
C3: A4 ELIMINATING DUPLICATES
C5: What are we doing here?
C6: We're going to get rid of duplicates to get a list of unique values.
C7: It's really easy, we just have to click lots of stuff in Excel's menu.
C9: This is amazing! What if I want to do more?
C10: Carefully read every single entry in Excel's help file… :D
C12: How do I get started again?
C13: This example is ready to go, just keep reading!
C14: If you need a reset, copy-paste the table at the bottom of this worksheet
C15: Once you think you understand, go do the easiest exercise yet!
A18: * | B18: INSTRUCTIONS
B19: Select the data for which you want to remove duplicates. In Excel's menu, select the "data" ribbon and then "Remove duplicates" from the "Data Tools" section
A21: * | B21: Data table | D21: Steps
A23: * | B23: Remove duplicates across two columns
B25: Count of item | C25: Item | D25: Select cells in the table to the right (B25 to C31)
B26: 1 | C26: Golden ring | D26: Click on the "data" ribbon, and then "Remove duplicates" in the "Data Tools" section.
B27: 1 | C27: Golden ring
B28: 4 | C28: Bears
B29: 2 | C29: Golden ring
B30: 1 | C30: Turtle Dove
B31: 5 | C31: Bears
D32: Make sure that there is a checkmark for "My data has headers" and that both columns are selected.
B33: Reset example (scroll down) | D33: Click "Ok". One duplicate value will be removed.
D34: "Golden ring" is in the list twice because it is paired with "1" in one row, and with "2" in another row.
A36: * | B36: Remove duplicates across one column
B38: Count of item | C38: Item | D38: When you want to find unique values in one column, it's easier to copy-paste it elsewhere.
B39: 1 | C39: Golden ring | D39: But for the sake of this demonstration, select cells in the table to the right (B38 to C44)
B40: 1 | C40: Golden ring | D40: Click on the "data" ribbon, and then "Remove duplicates" in the "Data Tools" section.
B41: 4 | C41: Bears | D41: Excel realizes that there is another column besides this one, but we don't want it.
B42: 2 | C42: Golden ring | D42: Select "Continue with the current selection" and then "Remove duplicates…"
B43: 1 | C43: Turtle Dove | D43: Make sure that there is a checkmark for "My data has headers".
B44: 5 | C44: Bears | D44: Click "Ok". Three duplicate values will be removed.
D45: The "Count of item" column no longer makes sense. Select cells B38 to B44 and delete them.
B46: Reset example (scroll down)
A48: * | B48: SUPPLEMENTARY INFORMATION
A50: * | B50: Conditional formatting
B52: Count of item | C52: Item
B53: 1 | C53: Golden ring
B54: 1 | C54: Golden ring
B55: 4 | C55: Bears
B56: 2 | C56: Golden ring
B57: 1 | C57: Turtle Dove
B58: 5 | C58: Bears
B60: Conditional formatting (Home ribbon, Styles section) has a "duplicate values" option under "highlight cell rules".
B61: It works very differently - it highlights any item that has a duplicate, leave empty of formatting items that are completely unique in a range.
B62: In our example table, "Turtle Dove" is only found in only one cell, so it's been left in the default format (white background).
B63: However, "Golden ring" is in three different cells, so it's been highlighted.
A65: * | B65: RESET EXAMPLES
B67: Count of item | C67: Item
B68: 1 | C68: Golden ring
B69: 1 | C69: Golden ring
B70: 4 | C70: Bears
B71: 2 | C71: Golden ring
B72: 1 | C72: Turtle Dove
B73: 5 | C73: Bears
B75: Copy the above table, and then click to teleport to the desired reset location. Paste.
B76: Because of how Excel handles links, you had to scroll down to get here.
B77: You may or may not need to scroll down when clicking on one of the two below example buttons.
B79: First Example (2 columns) | C79: Second example (1 column)

Sheet A4 Exercise
A1: * | B1: Main Menu | C1: Instructions | D1: Data worksheet
A3: * | B3: REMOVE DUPLICATES EXERCISE
B4: Don't worry, this one is REALLY easy. Go copy-paste columns A and B from the 2021 CSD worksheet
B5: into columns G and H of this worksheet. Then remove the duplicates. Easy!
B6: You should find 77 duplicate values, with 19 unique values remaining.
B7: Although sometimes these counts change a bit depending on the copy-paste method you used.
A8: *

Sheet A5 Instructions
A1: * | B1: Main Menu | C1: Exercise
C3: A5 FIND/REPLACE TRICKS
C5: What are we doing here?
C6: You're getting kind of tired, aren't you?
C7: Let's keep it very simple for now. We're… mostly going to look at
C8: some Find/Replace options. You can find text… and replace it with other text.
C10: This is amazing! What if I want to do more?
C11: Try out the options that I haven't covered.
C12: Google "find replace in Excel" to find a few tricks. And "Excel wildcards".
C14: How do I get started again?
C15: Just read the instructions, then go do the exercise.
A18: * | B18: INSTRUCTIONS
B19: You can access find/replace by using the Ctrl-F or Command-F shortcut key, and then clicking on the "replace" tab.
B20: Alternatively, you can click on "Find and select" in the "Edition" section of the "Home" ribbon, and then select "Replace".
B21: Or with a Mac, look at your special editing menu above Excel.
B23: Put in what you want to find in the first text box, and put in what you want to replace it with in the second text box.
B24: Click on options... to get more options.
B26: An interesting but tricky tip is using find/replace to quickly highlight cells that have specific text.
B27: Just click on the "format" button in the "replace by" section, don't input anything in the "replace by" box, and you're free to format the cells
B28: containing the text you're searching for in any way you'd like!
B29: To stop the behavior, click on the "Format" dropdown and select "Clear Replace Format".
B31: You can often clean up data by searching with exact match for cells containing only a space and replacing that with nothing at all.
B32: (Although there are also formulas that serve a similar function.)
B34: You can use * as a wildcard, or ? as a wildcard that only finds one character.
... B37: You can do find/replace for an entire worksheet, for an entire Excel file or only in a specified range of cells.
A39: * | B39: I think that you can go straight to the exercise!

Sheet A5 Exercise
A1: * | B1: Main Menu | C1: Instructions
A3: * | B3: FIND/REPLACE TRICKS EXERCISE
B4: 1 - Using the color of your choice, quickly highlight all cells that have a smiley face. That should be a total of 14 cells.
B5: 2 - Count the number of cells in this worksheet that contain the word face. The answer should be 3 (or 5 if you count instances in this section)
B6: 3 - Count the number of cells that contain the letter "e". The answer should be 11 if you only looked at the below text, 17 if you looked at the entire worksheet.
A8: * | B8: List to use to practice find/replace tricks
B9: I have a smiley face :) | C9: I have a frowny face :( | D9: :) yay yay
B10: It's cold :( | C10: I won the lottery :) | D10: I had to work late. :/
B11: I love chocolate :) | C11: I like cake :) | D11: I don't like ants :(
B12: Smiley faces scare me :( | C12: I'm having fun today :) | D12: :) :) :) :) :) :) :)
B13: I'm helping people with Excel :) | C13: I'm not feeling excellent :( | D13: You wouldn't find any of these cells with an exact match :(

Sheet B1 Instructions
B1: Main Menu | C1: Exercises
C3: B1 XLOOKUP
C5: What are we doing here?
C6: Xlookup... Looks things up for you!
C7: Answer questions like "is x in my main list". Or "I have x in
C8: another spreadsheet but I want it here everywhere it matches?"
C10: This is amazing! What if I want to do more?
C11: Index/Match is similar and helpful if you will be sharing with older versions of Excel.
C13: How do I get started again?
C14: Just read the instructions, then go do the exercises.
A17: * | B17: Page Menu
B18: Scroll down after selecting item in menu - desired instructions are at the bottom of the screen
B19: How to get XLookup to work
B20: What needs to be in place for XLookup to work
B21: Important XLookup notes
B22: XLookup versus VLookup versus Index/Match
A24: * | B24: INSTRUCTIONS | I24: Top
B25: Xlookup will put data in your cell by looking up values in another column. It has six arguments.
B26: First, it needs to know what it will be looking up.
B27: Second, it wants to know the array in which it will be looking up whatever it is you need it to look up.
B28: Third, it wants the "return array" - the columns from which it will be extracting data.
B29: Fourth, it optionally wants to know what it should do if a value it's looking up (in the first part) doesn't exist in the second part.
B30: Fifth, it optionally wants to need if it's looking for an exact match, the closest smaller item, the closest bigger item, or doing a wildcard search.
B31: Sixth, it optionally wants to know if it should be looking from top to bottom, from bottom to top, and whether or not the data has been sorted.
B33: Whenever you're working with ranges or arrays, it's usually a good idea to use the "$" symbols.
B34: Keep in mind that Xlookup never worries about capitalization.
B35: XLookup can get very complex. Start simple, and build complexity in as you get more comfortable!
A37: * | B37: Simple XLookup Example | I37: Top
B38: In the examples below, we have a nice table of sounds that animals make…
B39: …while Farmer Ted has a list of animals for which they would like to automatically associate sounds.
B41: Table of animals and the sounds that they make | E41: Farmer Ted's list of animals | G41: Simple Xlookup
B42: Animals | C42: Sounds | E42: Animal Names | F42: Animals | G42: Sounds
B43: Cat | C43: Miow | E43: Felix | F43: Cat | G43: =_xlfn.XLOOKUP(F43,$B$43:$B$49,$C$43:$C$49,"NOT FOUND!!!") -> Miow
B44: Giraffe | C44: ??? | E44: Spot | F44: Dog | G44: =_xlfn.XLOOKUP(F44,$B$43:$B$49,$C$43:$C$49,"NOT FOUND!!!") -> Woof
B45: Cricket | C45: Cricket cricket | E45: Hortense | F45: Giraffe | G45: =_xlfn.XLOOKUP(F45,$B$43:$B$49,$C$43:$C$49,"NOT FOUND!!!") -> ???
B46: Cow | C46: Mooo | E46: Rover | F46: Dog | G46: =_xlfn.XLOOKUP(F46,$B$43:$B$49,$C$43:$C$49,"NOT FOUND!!!") -> Woof
B47: Pig | C47: Oink oink | E47: Bacon | F47: Pig | G47: =_xlfn.XLOOKUP(F47,$B$43:$B$49,$C$43:$C$49,"NOT FOUND!!!") -> Oink oink
B48: Duck | C48: Quack quack | E48: Donald | F48: Duck | G48: =_xlfn.XLOOKUP(F48,$B$43:$B$49,$C$43:$C$49,"NOT FOUND!!!") -> Quack quack
B49: Dog | C49: Woof | E49: Jimmy | F49: Cricket | G49: =_xlfn.XLOOKUP(F49,$B$43:$B$49,$C$43:$C$49,"NOT FOUND!!!") -> Cricket cricket
E50: Barbecued | F50: Pig | G50: =_xlfn.XLOOKUP(F50,$B$43:$B$49,$C$43:$C$49,"NOT FOUND!!!") -> Oink oink
D51: No Gators in table of animals -> | E51: Later | F51: Gator | G51: =_xlfn.XLOOKUP(F51,$B$43:$B$49,$C$43:$C$49,"NOT FOUND!!!") -> NOT FOUND!!!
E52: Tournedos | F52: Pig | G52: =_xlfn.XLOOKUP(F52,$B$43:$B$49,$C$43:$C$49,"NOT FOUND!!!") -> Oink oink
E53: Soushi | F53: Cat | G53: =_xlfn.XLOOKUP(F53,$B$43:$B$49,$C$43:$C$49,"NOT FOUND!!!") -> Miow
G54: =XLOOKUP(F43,$B$43:$B$49,$C$43:$C$49,"NOT FOUND!!!")
A56: * | B56: In-depth look at the Xlookup formula
B57: =XLOOKUP(F43,$B$43:$B$49,$C$43:$C$49,"NOT FOUND!!!")
B58: First, we tell Excel we want to lookup "Cat" or whatever is contained in cell F43.
B59: Second, we tell Excel we'll be looking that up in our table of animal sounds, in array B43 to B49 ($B$43:$B$49) - our column of animals
B60: Third, we tell Excel we want it to give us the corresponding sound from our table of animal sounds in array C43 to C49 ($C$43:$C$49).
B61: Animals are in B column, sounds in the C column. So look for "Cat", and tell us what sound the "cat" makes.
B62: Fourth "NOT FOUND!!!" tells Excel that if the animal doesn't exist, tell us that it wasn't found.
B63: Fifth, we left off the optional match argument. The default is to look for an exact match, so that's what XLookup is doing.
B64: Sixth, we left off the optional search mode argument. The default is to go from top to bottom, so that's what XLookup is doing.
A66: * | B66: What needs to be in place for Xlookup to work | I66: Top
B67: XLookup is only available in Excel for Microsoft 365, Excel 2021, or Excel for the web.
B69: You need a table of unique values or unique set of values for which there are other values in the same row that you need returned.
B70: Basically, a "reference" table full of information you want to look up. A list of prices per products, a list of patients with their characteristics, a list of books, etc.
B72: For the fifth argument of XLookup, you'll want to google how to use wildcards if selecting that option (which allows for fuzzy matches).
B73: You'll likely want to be looking up numbers if selecting the options for the closest smaller or closest bigger match.
B75: For the sixth argument of Xlookup, if not using the default, you'll likely want to have your data already sorted.
B76: This can speed up the search and your entire Excel file!
A78: * | B78: Important XLookup Notes | I78: Top
B79: If you're having trouble matching cells that contain text, learn about the TRIM or CLEAN formulas.
A81: * | B81: XLookup with wildcards example
B82: Vlookup also works with wildcards. Like "*" & F86 & "*". Um…just…look at the example, I guess.
B84: Table of animals and the sounds that they make | E84: Farmer Ted's list of animals
B85: Fuzzy animals - Exact matches won't work | C85: Sounds | E85: Animal Names | F85: Animals | G85: Simple XLookup | H85: With Wildcards
B86: A cat | C86: Miow | E86: Felix | F86: Cat | G86: =_xlfn.XLOOKUP("*"&F86&"*",$B$86:$B$92,$C$86:$C$92,"NOT FOUND!!!") -> NOT FOUND!!! | H86: =_xlfn.XLOOKUP("*"&F86&"*",$B$86:$B$92,$C$86:$C$92,"NOT FOUND!!!",2) -> Miow
B87: The giraffe | C87: ??? | E87: Spot | F87: Dog | G87: =_xlfn.XLOOKUP("*"&F87&"*",$B$86:$B$92,$C$86:$C$92,"NOT FOUND!!!") -> NOT FOUND!!! | H87: =_xlfn.XLOOKUP("*"&F87&"*",$B$86:$B$92,$C$86:$C$92,"NOT FOUND!!!",2) -> Woof
B88: Cricket Cricket | C88: Cricket cricket | E88: Hortense | F88: Giraffe | G88: =_xlfn.XLOOKUP("*"&F88&"*",$B$86:$B$92,$C$86:$C$92,"NOT FOUND!!!") -> NOT FOUND!!! | H88: =_xlfn.XLOOKUP("*"&F88&"*",$B$86:$B$92,$C$86:$C$92,"NOT FOUND!!!",2) -> ???
B89: Wow Cow | C89: Mooo | E89: Rover | F89: Dog | G89: =_xlfn.XLOOKUP("*"&F89&"*",$B$86:$B$92,$C$86:$C$92,"NOT FOUND!!!") -> NOT FOUND!!! | H89: =_xlfn.XLOOKUP("*"&F89&"*",$B$86:$B$92,$C$86:$C$92,"NOT FOUND!!!",2) -> Woof
B90: Big pig | C90: Oink oink | E90: Bacon | F90: Pig | G90: =_xlfn.XLOOKUP("*"&F90&"*",$B$86:$B$92,$C$86:$C$92,"NOT FOUND!!!") -> NOT FOUND!!! | H90: =_xlfn.XLOOKUP("*"&F90&"*",$B$86:$B$92,$C$86:$C$92,"NOT FOUND!!!",2) -> Oink oink
B91: Duck goose | C91: Quack quack | E91: Donald | F91: Duck | G91: =_xlfn.XLOOKUP("*"&F91&"*",$B$86:$B$92,$C$86:$C$92,"NOT FOUND!!!") -> NOT FOUND!!! | H91: =_xlfn.XLOOKUP("*"&F91&"*",$B$86:$B$92,$C$86:$C$92,"NOT FOUND!!!",2) -> Quack quack
B92: Wow dog wow | C92: Woof | E92: Jimmy | F92: Cricket | G92: =_xlfn.XLOOKUP("*"&F92&"*",$B$86:$B$92,$C$86:$C$92,"NOT FOUND!!!") -> NOT FOUND!!! | H92: =_xlfn.XLOOKUP("*"&F92&"*",$B$86:$B$92,$C$86:$C$92,"NOT FOUND!!!",2) -> Cricket cricket
E93: Barbecued | F93: Pig | G93: =_xlfn.XLOOKUP("*"&F93&"*",$B$86:$B$92,$C$86:$C$92,"NOT FOUND!!!") -> NOT FOUND!!! | H93: =_xlfn.XLOOKUP("*"&F93&"*",$B$86:$B$92,$C$86:$C$92,"NOT FOUND!!!",2) -> Oink oink
D94: No Gators in table of animals -> | E94: Later | F94: Gator | G94: =_xlfn.XLOOKUP("*"&F94&"*",$B$86:$B$92,$C$86:$C$92,"NOT FOUND!!!") -> NOT FOUND!!! | H94: =_xlfn.XLOOKUP("*"&F94&"*",$B$86:$B$92,$C$86:$C$92,"NOT FOUND!!!",2) -> NOT FOUND!!!
E95: Tournedos | F95: Pig | G95: =_xlfn.XLOOKUP("*"&F95&"*",$B$86:$B$92,$C$86:$C$92,"NOT FOUND!!!") -> NOT FOUND!!! | H95: =_xlfn.XLOOKUP("*"&F95&"*",$B$86:$B$92,$C$86:$C$92,"NOT FOUND!!!",2) -> Oink oink
E96: Soushi | F96: Cat | G96: =_xlfn.XLOOKUP("*"&F96&"*",$B$86:$B$92,$C$86:$C$92,"NOT FOUND!!!") -> NOT FOUND!!! | H96: =_xlfn.XLOOKUP("*"&F96&"*",$B$86:$B$92,$C$86:$C$92,"NOT FOUND!!!",2) -> Miow
G97: =XLOOKUP("*"&F86&"*",$B$86:$B$92,$C$86:$C$92,"NOT FOUND!!!") | H97: Simple
G98: =XLOOKUP("*"&F86&"*",$B$86:$B$92,$C$86:$C$92,"NOT FOUND!!!",2) | H98: With Wildcards
A100: * | B100: XLookup returning an array example
B101: XLookup can return more than one column at a time!
B103: Table of animals and the sounds that they make and how nice from 1 to 5 | F103: Farmer Ted's list of animals
B104: Animals | C104: Sounds | D104: Nice | F104: Animal Names | G104: Animals | H104: Sounds | I104: Nice (filled in magically)
B105: Cat | C105: Miow | D105: 5 | F105: Felix | G105: Cat | H105: {=_xlfn.XLOOKUP(G105,$B$105:$B$111,$C$105:$D$111,"NOT FOUND!!!")} -> Miow | I105: 5
B106: Giraffe | C106: ??? | D106: 3 | F106: Spot | G106: Dog | H106: {=_xlfn.XLOOKUP(G106,$B$105:$B$111,$C$105:$D$111,"NOT FOUND!!!")} -> Woof | I106: 5
B107: Cricket | C107: Cricket cricket | D107: 1 | F107: Hortense | G107: Giraffe | H107: {=_xlfn.XLOOKUP(G107,$B$105:$B$111,$C$105:$D$111,"NOT FOUND!!!")} -> ??? | I107: 3
B108: Cow | C108: Mooo | D108: 4 | F108: Rover | G108: Dog | H108: {=_xlfn.XLOOKUP(G108,$B$105:$B$111,$C$105:$D$111,"NOT FOUND!!!")} -> Woof | I108: 5
B109: Pig | C109: Oink oink | D109: 2 | F109: Bacon | G109: Pig | H109: {=_xlfn.XLOOKUP(G109,$B$105:$B$111,$C$105:$D$111,"NOT FOUND!!!")} -> Oink oink | I109: 2
B110: Duck | C110: Quack quack | D110: 3 | F110: Donald | G110: Duck | H110: {=_xlfn.XLOOKUP(G110,$B$105:$B$111,$C$105:$D$111,"NOT FOUND!!!")} -> Quack quack | I110: 3
B111: Dog | C111: Woof | D111: 5 | F111: Jimmy | G111: Cricket | H111: {=_xlfn.XLOOKUP(G111,$B$105:$B$111,$C$105:$D$111,"NOT FOUND!!!")} -> Cricket cricket | I111: 1
F112: Barbecued | G112: Pig | H112: {=_xlfn.XLOOKUP(G112,$B$105:$B$111,$C$105:$D$111,"NOT FOUND!!!")} -> Oink oink | I112: 2
E113: No Gators in table of animals -> | F113: Later | G113: Gator | H113: {=_xlfn.XLOOKUP(G113,$B$105:$B$111,$C$105:$D$111,"NOT FOUND!!!")} -> NOT FOUND!!!
F114: Tournedos | G114: Pig | H114: {=_xlfn.XLOOKUP(G114,$B$105:$B$111,$C$105:$D$111,"NOT FOUND!!!")} -> Oink oink | I114: 2
F115: Soushi | G115: Cat | H115: {=_xlfn.XLOOKUP(G115,$B$105:$B$111,$C$105:$D$111,"NOT FOUND!!!")} -> Miow | I115: 5
H116: =XLOOKUP(G105,$B$105:$B$111,$C$105:$D$111,"NOT FOUND!!!")
A118: * | B118: XLookup looking with multiple conditions
B119: You can match values on more than one condition in XLookup which involves some hideous array math!
B121: Table of cats and the sounds that they make and how nice from 1 to 5 | F121: Farmer Ted's list of cats and their favorite sound
B122: Animals | C122: Sounds | D122: Nice | F122: Animal Names | G122: Animals | H122: Sounds | I122: Nice
...

Sheet B1 Exercise
B1: Main Menu | C1: Instructions
B3: XLookup Exercises
A5: * | B5: Page Menu
B6: Scroll down after selecting item in menu - desired instructions are at the bottom of the screen
B7: Exercise 1: Just like your "How To" notes!
B8: Exercise 2: Celebrities and cities
B9: Exercise 3: Superhero equipment is expensive!
B10: Exercise 4: You can count on movies!
B11: Exercise 5: Comparing apples and oranges
B12: Demo: A magical dropdown
B14: Exercise 1: Just like in your "How To" notes! | I14: Top
B16: Instructions
B17: Farmer Ted has acquired a few new animals. Help them identify the sounds their animals make.
B18: Use XLookup identify sounds in column G. If an animal doesn't exist, put in a blank ("")
B20: Table with values to look up | E20: Your table with values to find
B21: Animals | C21: Sounds | E21: Animal Name | F21: Type of Animal | G21: Look up the sound
B22: Bird | C22: Tweet Tweet | E22: Bacon | F22: Pig | T22: Oink oink
B23: Cat | C23: Miow | E23: Big | F23: Bird | T23: Tweet Tweet
B24: Cow | C24: Mooo | E24: Chops | F24: Pig | T24: Oink oink
B25: Cricket | C25: Cricket cricket | E25: Donald | F25: Duck | T25: Quack quack
B26: Dog | C26: Woof | E26: Felix | F26: Cat | T26: Miow
B27: Duck | C27: Quack quack | E27: Hortense | F27: Giraffe | T27: ???
B28: Giraffe | C28: ??? | E28: Jimmy | F28: Cricket | T28: Cricket cricket
B29: Kangaroo | C29: Who knows? | E29: Later | F29: Gator
B30: Pig | C30: Oink oink | E30: Rover | F30: Dog | T30: Woof
E31: Spot | F31: Dog | T31: Woof
E32: Sprinkles | F32: Cat | T32: Miow
E33: Tournedos | F33: Pig | T33: Oink oink
E34: Tweety | F34: Bird | T34: Tweet Tweet
B37: Exercise 2: Celebrities and cities | I37: Top
B39: Instructions
B40: You've been compiling a list of famous people, the city and country they come from, and how the average temperature of that city had an impact on their career.
B41: However, you're a busy person! You can't be expected to type up the country and the temperature each time you put in the name of the city.
B42: So to speed things up here, use Xlookup to find the appropriate country in column H, and magically load the status/temperature in column I.
B44: Table with values to look up | F44: Your table with values to find
B45: City | C45: Country | D45: Status | F45: Celebrities | G45: City of origin | H45: Look up the country | I45: Look up the status
B46: Moncton | C46: Canada | D46: Cold and wet | F46: Atwood, Margaret | G46: Ottawa | T46: Canada | U46: Cold
B47: Ottawa | C47: Canada | D47: Cold | F47: Bastarache, Michel | G47: Moncton | T47: Canada | U47: Cold and wet
B48: Winnipeg | C48: Canada | D48: Colder | F48: Claus, Santa | G48: Christmas Village | T48: North Pole | U48: Magical
B49: Honolulu | C49: Hawaii | D49: Nice and warm | F49: Fox, Terry | G49: Winnipeg | T49: Canada | U49: Colder
B50: Christmas Village | C50: North Pole | D50: Magical | F50: Kay, Guy Gavriel | G50: Winnipeg | T50: Canada | U50: Colder
B51: Las Vegas | C51: United States | D51: Too hot | F51: Keith, Alexander | G51: Halifax | T51: Canada | U51: So much rain
B52: Halifax | C52: Canada | D52: So much rain | F52: Mars, Bruno | G52: Honolulu | T52: Hawaii | U52: Nice and warm
F53: McLachlan, Sarah | G53: Halifax | T53: Canada | U53: So much rain
F54: Morissette, Alanis | G54: Ottawa | T54: Canada | U54: Cold
F55: Obama, Barack | G55: Honolulu | T55: Hawaii | U55: Nice and warm
F56: Roy, Gabrielle | G56: Winnipeg | T56: Canada | U56: Colder
F57: Sinatra, Frank | G57: Las Vegas | T57: United States | U57: Too hot
B59: Exercise 3: Superhero equipment is expensive! | I59: Top
B61: Instructions
B62: You need to calculate how much various heroes have been spending on their equipment.
B63: Lookup information in not one but two different tables!
B65: Table with equipment to look up | E65: Table with heroes to look up
B66: Equipment | C66: Item Cost | E66: ID | F66: Civilian Identity | G66: Hero Name
B67: Cape | C67: 300 | E67: 1 | F67: Al Draped | G67: Mouse
B68: First aid kit | C68: 20 | E68: 2 | F68: Brute Vain | G68: Ratman
B69: Makeshift uniforms | C69: 50 | E69: 3 | F69: Gene Gray | G69: Ashes
B70: Rat Car | C70: 82500 | E70: 4 | F70: Karl Tent | G70: Stupendousman
B71: Ratarangs | C71: 500 | E71: 5 | F71: Marg Bordon | G71: Ratwoman
B72: Redacted | C72: 1000 | E72: 6 | F72: Natalie Rovanov | G72: Black Recluse
B73: Reinforced uniforms | C73: 800 | E73: 7 | F73: Pewter Parking | G73: Webman
B74: Small invisible plane | C74: 800000
B75: Zeta Ray Emitters | C75: 60
B77: Your table with values to find
B79: ID | C79: Equipment purchase | D79: Quantity | E79: Look Up Item Cost | F79: Look Up Hero Name | G79: Total Cost
B80: 6 | C80: Reinforced uniforms | D80: 1 | G80: =D80*E80 -> 0 | T80: 800 | U80: Black Recluse
B81: 3 | C81: Cape | D81: 2 | G81: =D81*E81 -> 0 | T81: 300 | U81: Ashes
B82: 3 | C82: First aid kit | D82: 5 | G82: =D82*E82 -> 0 | T82: 20 | U82: Ashes
B83: 6 | C83: Redacted | D83: 10 | G83: =D83*E83 -> 0 | T83: 1000 | U83: Black Recluse
B84: 2 | C84: Cape | D84: 5 | G84: =D84*E84 -> 0 | T84: 300 | U84: Ratman
B85: 2 | C85: First aid kit | D85: 10 | G85: =D85*E85 -> 0 | T85: 20 | U85: Ratman
B86: 7 | C86: Makeshift uniforms | D86: 1 | G86: =D86*E86 -> 0 | T86: 50 | U86: Webman
B87: 2 | C87: Reinforced uniforms | D87: 5 | G87: =D87*E87 -> 0 | T87: 800 | U87: Ratman
B88: 2 | C88: Rat Car | D88: 1 | G88: =D88*E88 -> 0 | T88: 82500 | U88: Ratman
B89: 2 | C89: Ratarangs | D89: 50 | G89: =D89*E89 -> 0 | T89: 500 | U89: Ratman
B90: 4 | C90: Cape | D90: 2 | G90: =D90*E90 -> 0 | T90: 300 | U90: Stupendousman
B92: Bonus table that uses the information you looked up and SUMIFS to calculate the total purchases for each hero
B94: Hero Name | C94: Total Purchases
B95: Ashes | C95: =SUMIFS($G$80:$G$90,$F$80:$F$90,B95) -> 0
B96: Black Recluse | C96: =SUMIFS($G$80:$G$90,$F$80:$F$90,B96) -> 0
B97: Mouse | C97: =SUMIFS($G$80:$G$90,$F$80:$F$90,B97) -> 0
B98: Ratman | C98: =SUMIFS($G$80:$G$90,$F$80:$F$90,B98) -> 0
B99: Ratwoman | C99: =SUMIFS($G$80:$G$90,$F$80:$F$90,B99) -> 0
B100: Stupendousman | C100: =SUMIFS($G$80:$G$90,$F$80:$F$90,B100) -> 0
B101: Webman | C101: =SUMIFS($G$80:$G$90,$F$80:$F$90,B101) -> 0
B103: Exercise 4: You can count on movies! | I103: Top
B105: Instructions
B106: You want to make a list of movies that have numbers in them, in numerical order!
B107: You may want to review the Xlookup with wildcards example.
B109: Table with values to look up | E109: Your table with values to find
B110: Movie name | E110: Number | F110: Movie name
B111: Avatar | E111: One | T111: One Flew Over the Cuckoo's Nest
B112: Avatar: The Way of Water | E112: Two | T112: Two for the Money
B113: Avengers: Endgame | E113: Three | T113: Three Kings
B114: Avengers: Infinity War | E114: Four | T114: Fantastic Four
B115: Barbie | E115: Five | T115: Slaughterhouse-Five
B116: Eight Below | E116: Six | T116: The Sixth Sense
B117: Fantastic Four | E117: Seven | T117: Seven
B118: Frozen II | E118: Eight | T118: Eight Below
B119: Furious 7 | E119: Nine | T119: The Nines
...

Sheet B2 Instructions
A1: * | B1: Main Menu | C1: Exercise
C3: B2 OR, AND, IF, and IFS
C5: What are we doing here?
C6: We're looking at some logic formulas.
C7: IF and IFS which lets you return what you want according to a criteria.
C8: AND which checks if one or more criteria are all true.
C9: OR which checks if at least one criteria is true.
C11: This is amazing! What if I want to do more?
C12: I don't know? Maybe look up boolean operators?
C13: A lot of what we do here is boolean logic.
C14: And definitely look up TRIM, and UPPER and LOWER.
C16: How do I get started again?
C17: This example is ready to go, just keep reading!
... C19: Once you think you understand, go do the exercise!
A22: * | B22: INSTRUCTIONS
B23: The IF formula takes a criteria, usually in the form of a comparison such as if a cell is equal, or bigger, or smaller than a given value.
B24: The next two arguments are optional but I recommend always entering them. They let you decide what is returned by the IF formula.
B25: A value if the criteria is true, or a value if the criteria is false.
B27: The IFS formula takes a criteria, than it needs to know what to return if that criteria is true.
B28: Rinse and repeat for all your criteria. It stops its work once it finds that something is true.
B29: As the last two arguments, you can put in TRUE followed by what the IFS formula should return if nothing else in the list of conditions was true.
B31: The AND and OR formulas return "True" or "False".
B32: The AND formula requires that ALL criteria be met in order for the formula to return "TRUE".
B33: The OR formula requires that at least one of the criteria be met in order for the formula to return "TRUE".
B35: You can have the IF formula return a blank by entering "" as the value if true or false,
B36: and a number like 0 or 1 by simply putting in the number without quotation marks.
B37: And you can use an AND or OR formula within an IF formula.
A39: * | B39: Scariness table and criteria | H39: Formulas
A41: * | B41: Simple IF example
B42: Let's flag all the cases where the scariness is 5 or more.
B44: Horror source | C44: Nature | D44: Scariness (out of 10) | E44: Amount | F44: Distance (km) | H44: Simple IF formula
B45: Bermuda Triangle | C45: Phenomenon | D45: 5 | E45: 1 | F45: 2290 | H45: =IF(D45>=5,"I AM CONCERNED", "NOTHING TO SEE HERE") -> I AM CONCERNED | I45: =IF(D45>=5,"I AM CONCERNED", "NOTHING TO SEE HERE")
B46: Vampires | C46: Monster | D46: 4 | E46: 0 | F46: 10 | H46: =IF(D46>=5,"I AM CONCERNED", "NOTHING TO SEE HERE") -> NOTHING TO SEE HERE
B47: Zombies | C47: Monster | D47: 9 | E47: 0 | F47: 10 | H47: =IF(D47>=5,"I AM CONCERNED", "NOTHING TO SEE HERE") -> I AM CONCERNED
B48: Germs | C48: Natural | D48: 5 | E48: 100000000 | F48: 1 | H48: =IF(D48>=5,"I AM CONCERNED", "NOTHING TO SEE HERE") -> I AM CONCERNED
B49: Unfulfillment | C49: Philosophical | D49: 10 | E49: 0 | F49: 0 | H49: =IF(D49>=5,"I AM CONCERNED", "NOTHING TO SEE HERE") -> I AM CONCERNED
B50: Noises | C50: Phenomenon | D50: 1 | E50: 12 | F50: 0 | H50: =IF(D50>=5,"I AM CONCERNED", "NOTHING TO SEE HERE") -> NOTHING TO SEE HERE
B51: Loch Ness Monster | C51: Monster | D51: 3 | E51: 1 | F51: 4218 | H51: =IF(D51>=5,"I AM CONCERNED", "NOTHING TO SEE HERE") -> NOTHING TO SEE HERE
B53: It might be best to assign a cell for the criteria - what if we change our minds about how much scariness we can tolerate?
B54: Scariness criteria | C54: 5 | D54: <- Try changing this number and see what happens in the "Simple worry" column of the below table.
B56: Horror source | C56: Nature | D56: Scariness (out of 10) | E56: Amount | F56: Distance (km) | H56: Simple IF formula with a cell address for the criteria
B57: Bermuda Triangle | C57: Phenomenon | D57: 5 | E57: 1 | F57: 2290 | H57: =IF(D57>=$C$54,"I AM CONCERNED", "Nothing to see here") -> I AM CONCERNED | I57: =IF(D57>=$C$54,"I AM CONCERNED", "Nothing to see here")
B58: Vampires | C58: Monster | D58: 4 | E58: 0 | F58: 10 | H58: =IF(D58>=$C$54,"I AM CONCERNED", "Nothing to see here") -> Nothing to see here
B59: Zombies | C59: Monster | D59: 9 | E59: 0 | F59: 10 | H59: =IF(D59>=$C$54,"I AM CONCERNED", "Nothing to see here") -> I AM CONCERNED
B60: Germs | C60: Natural | D60: 5 | E60: 100000000 | F60: 1 | H60: =IF(D60>=$C$54,"I AM CONCERNED", "Nothing to see here") -> I AM CONCERNED
B61: Unfulfillment | C61: Philosophical | D61: 10 | E61: 0 | F61: 0 | H61: =IF(D61>=$C$54,"I AM CONCERNED", "Nothing to see here") -> I AM CONCERNED
B62: Noises | C62: Phenomenon | D62: 1 | E62: 12 | F62: 0 | H62: =IF(D62>=$C$54,"I AM CONCERNED", "Nothing to see here") -> Nothing to see here
B63: Loch Ness Monster | C63: Monster | D63: 3 | E63: 1 | F63: 4218 | H63: =IF(D63>=$C$54,"I AM CONCERNED", "Nothing to see here") -> Nothing to see here
B65: AND example
B66: ="Let's flag all the cases where the scariness is "& C67 &" or more and the threat is within " &F67 &" KM" -> Let's flag all the cases where the scariness is 5 or more and the threat is within 10 KM
B67: Scariness criteria | C67: 5 | E67: Distance | F67: 10
B69: Horror source | C69: Nature | D69: Scariness (out of 10) | E69: Amount | F69: Distance (km) | H69: AND formula - True means we are worried
B70: Bermuda Triangle | C70: Phenomenon | D70: 5 | E70: 1 | F70: 2290 | H70: =AND(D70>=$C$67,F70<=$F$67) -> FALSE | I70: =AND(D70>=$C$67,F70<=$F$67)
B71: Vampires | C71: Monster | D71: 4 | E71: 0 | F71: 10 | H71: =AND(D71>=$C$67,F71<=$F$67) -> FALSE
B72: Zombies | C72: Monster | D72: 9 | E72: 0 | F72: 10 | H72: =AND(D72>=$C$67,F72<=$F$67) -> TRUE
B73: Germs | C73: Natural | D73: 5 | E73: 100000000 | F73: 1 | H73: =AND(D73>=$C$67,F73<=$F$67) -> TRUE
B74: Unfulfillment | C74: Philosophical | D74: 10 | E74: 0 | F74: 0 | H74: =AND(D74>=$C$67,F74<=$F$67) -> TRUE
B75: Noises | C75: Phenomenon | D75: 1 | E75: 12 | F75: 0 | H75: =AND(D75>=$C$67,F75<=$F$67) -> FALSE
B76: Loch Ness Monster | C76: Monster | D76: 3 | E76: 1 | F76: 4218 | H76: =AND(D76>=$C$67,F76<=$F$67) -> FALSE
B78: OR example
B79: ="Let's flag all the cases where the scariness is "&C80&" or more or the threat is within "&F80&" KM" -> Let's flag all the cases where the scariness is 5 or more or the threat is within 10 KM
B80: Scariness criteria | C80: 5 | E80: Distance | F80: 10
B82: Horror source | C82: Nature | D82: Scariness (out of 10) | E82: Amount | F82: Distance (km) | H82: OR formula - True means we are worried
B83: Bermuda Triangle | C83: Phenomenon | D83: 5 | E83: 1 | F83: 2290 | H83: =OR(D83>=$C$80,F83<=$F$80) -> TRUE | I83: =OR(D83>=$C$80,F83<=$F$80)
B84: Vampires | C84: Monster | D84: 4 | E84: 0 | F84: 10 | H84: =OR(D84>=$C$80,F84<=$F$80) -> TRUE
B85: Zombies | C85: Monster | D85: 9 | E85: 0 | F85: 10 | H85: =OR(D85>=$C$80,F85<=$F$80) -> TRUE
B86: Germs | C86: Natural | D86: 5 | E86: 100000000 | F86: 1 | H86: =OR(D86>=$C$80,F86<=$F$80) -> TRUE
B87: Unfulfillment | C87: Philosophical | D87: 10 | E87: 0 | F87: 0 | H87: =OR(D87>=$C$80,F87<=$F$80) -> TRUE
B88: Noises | C88: Phenomenon | D88: 1 | E88: 12 | F88: 0 | H88: =OR(D88>=$C$80,F88<=$F$80) -> TRUE
B89: Loch Ness Monster | C89: Monster | D89: 3 | E89: 1 | F89: 4218 | H89: =OR(D89>=$C$80,F89<=$F$80) -> FALSE
B91: IF and AND example
B92: ="Let's flag all the cases where the scariness is "&C93&" or more and the threat is within "&F93&" KM" -> Let's flag all the cases where the scariness is 5 or more and the threat is within 10 KM
B93: Scariness criteria | C93: 5 | E93: Distance | F93: 10
B95: Horror source | C95: Nature | D95: Scariness (out of 10) | E95: Amount | F95: Distance (km) | H95: IF and AND formula
B96: Bermuda Triangle | C96: Phenomenon | D96: 5 | E96: 1 | F96: 2290 | H96: =IF(AND(D96>=$C$93,F96<=$F$93),"I AM CONCERNED","This is fine!") -> This is fine! | I96: =IF(AND(D96>=$C$93,F96<=$F$93),"I AM CONCERNED","This is fine!")
B97: Vampires | C97: Monster | D97: 4 | E97: 0 | F97: 10 | H97: =IF(AND(D97>=$C$93,F97<=$F$93),"I AM CONCERNED","This is fine!") -> This is fine!
B98: Zombies | C98: Monster | D98: 9 | E98: 0 | F98: 10 | H98: =IF(AND(D98>=$C$93,F98<=$F$93),"I AM CONCERNED","This is fine!") -> I AM CONCERNED
B99: Germs | C99: Natural | D99: 5 | E99: 100000000 | F99: 1 | H99: =IF(AND(D99>=$C$93,F99<=$F$93),"I AM CONCERNED","This is fine!") -> I AM CONCERNED
B100: Unfulfillment | C100: Philosophical | D100: 10 | E100: 0 | F100: 0 | H100: =IF(AND(D100>=$C$93,F100<=$F$93),"I AM CONCERNED","This is fine!") -> I AM CONCERNED
B101: Noises | C101: Phenomenon | D101: 1 | E101: 12 | F101: 0 | H101: =IF(AND(D101>=$C$93,F101<=$F$93),"I AM CONCERNED","This is fine!") -> This is fine!
B102: Loch Ness Monster | C102: Monster | D102: 3 | E102: 1 | F102: 4218 | H102: =IF(AND(D102>=$C$93,F102<=$F$93),"I AM CONCERNED","This is fine!") -> This is fine!
B104: IFS
B105: ="Let's flag all the cases where the scariness is "&C106&" or more as very scary and scariness of "&F106&" or more as sort of scary." -> Let's flag all the cases where the scariness is 7 or more as very scary and scariness of 5 or more as sort of scary.
B106: Scariness criteria 1 | C106: 7 | E106: Criteria 2 | F106: 5
B108: Horror source | C108: Nature | D108: Scariness (out of 10) | E108: Amount | F108: Distance (km) | H108: IF and AND formula
B109: Bermuda Triangle | C109: Phenomenon | D109: 5 | E109: 1 | F109: 2290 | H109: {=_xlfn.IFS(D109>=$C$106,"VERY SCARY",D109>=$F$106,"Sort of scary", TRUE, "This is fine!")} -> Sort of scary | I109: =IFS(D109>=$C$106,"VERY SCARY",D109>=$F$106,"Sort of scary", TRUE, "This is fine!")
B110: Vampires | C110: Monster | D110: 4 | E110: 0 | F110: 10 | H110: {=_xlfn.IFS(D110>=$C$106,"VERY SCARY",D110>=$F$106,"Sort of scary", TRUE, "This is fine!")} -> This is fine!
B111: Zombies | C111: Monster | D111: 9 | E111: 0 | F111: 10 | H111: {=_xlfn.IFS(D111>=$C$106,"VERY SCARY",D111>=$F$106,"Sort of scary", TRUE, "This is fine!")} -> VERY SCARY
B112: Germs | C112: Natural | D112: 5 | E112: 100000000 | F112: 1 | H112: {=_xlfn.IFS(D112>=$C$106,"VERY SCARY",D112>=$F$106,"Sort of scary", TRUE, "This is fine!")} -> Sort of scary
B113: Unfulfillment | C113: Philosophical | D113: 10 | E113: 0 | F113: 0 | H113: {=_xlfn.IFS(D113>=$C$106,"VERY SCARY",D113>=$F$106,"Sort of scary", TRUE, "This is fine!")} -> VERY SCARY
B114: Noises | C114: Phenomenon | D114: 1 | E114: 12 | F114: 0 | H114: {=_xlfn.IFS(D114>=$C$106,"VERY SCARY",D114>=$F$106,"Sort of scary", TRUE, "This is fine!")} -> This is fine!
B115: Loch Ness Monster | C115: Monster | D115: 3 | E115: 1 | F115: 4218 | H115: {=_xlfn.IFS(D115>=$C$106,"VERY SCARY",D115>=$F$106,"Sort of scary", TRUE, "This is fine!")} -> This is fine!

Sheet B2 Exercise
A1: * | B1: Main Menu | C1: Instructions
A3: * | B3: IF, AND, and OR EXERCISE
B4: You are worried about the various threats that surround you at all times.
B5: Use a combination of the IF and AND formulas to flag cases with "BE VERY WORRIED" in column H (Big Worry)
B6: where the scariness is at least 5, the amount of a thing is at least 1, and the distance is 10 or lower.
B8: Then, flag cases with "Maybe worry" in column I (Small Worry) where the scariness is at least 8,
B9: or where the amount is higher or equal to 50, or the distance is 10 or lower.
A10: * | B10: Criteria
C11: Scariness of at least | E11: Amount of at least | G11: Distance of no more than
B12: Big worry | C12: 5 | D12: and | E12: 1 | F12: and | G12: 10
B13: Small worry | C13: 8 | D13: or | E13: 50 | F13: or | G13: 10
A15: * | B15: Table of threats | H15: Tables of worries by criteria
B16: Horror source | C16: Nature | D16: Scariness (out of 10) | E16: Amount | F16: Distance (km) | H16: Big Worry | I16: Small Worry
B17: Bermuda Triangle | C17: Phenomenon | D17: 5 | E17: 1 | F17: 2290
B18: Vampires | C18: Monster | D18: 4 | E18: 0 | F18: 10 | J18: <-
B19: Zombies | C19: Monster | D19: 9 | E19: 0 | F19: 10 | J19: <-
B20: Germs | C20: Natural | D20: 5 | E20: 100000000 | F20: 1 | G20: -> | J20: <-
B21: Unfulfillment | C21: Philosophical | D21: 10 | E21: 0 | F21: 0 | J21: <-
B22: Noises | C22: Phenomenon | D22: 1 | E22: 12 | F22: 0 | J22: <-
B23: Loch Ness Monster | C23: Monster | D23: 3 | E23: 1 | F23: 4218
A25: * | B25: IFS exercise
B26: You are worried about the various threats that surround you at all times and find natural threats particularly scary
B27: Use the IFS formula to identify any threat that is natural in nature as "SO SCARY".
B28: Identify any other threat of 6 or more as "ALSO SCARY".
B29: And anything else as "This is fine!".
A30: * | B30: Criteria
B31: Condition | C31: Value | D31: Result
B32: If nature of threat is.. | C32: Natural | D32: SO SCARY
B33: Scariness equal to or more than | C33: 6 | D33: ALSO SCARY
B34: Anything else | D34: This is fine!
A36: * | B36: Table of threats | H36: Table of worries by criteria
B37: Horror source | C37: Nature | D37: Scariness (out of 10) | E37: Amount | F37: Distance (km) | H37: How scary is this?
B38: Bermuda Triangle | C38: Phenomenon | D38: 5 | E38: 1 | F38: 2290
B39: Vampires | C39: Monster | D39: 4 | E39: 0 | F39: 10
B40: Zombies | C40: Monster | D40: 9 | E40: 0 | F40: 10 | I40: <-
B41: Germs | C41: Natural | D41: 5 | E41: 100000000 | F41: 1 | G41: ->
B42: Unfulfillment | C42: Philosophical | D42: 10 | E42: 0 | F42: 0 | I42: <-
B43: Noises | C43: Phenomenon | D43: 1 | E43: 12 | F43: 0
B44: Loch Ness Monster | C44: Monster | D44: 3 | E44: 1 | F44: 4218

Sheet B3 Instructions
A1: * | B1: Main Menu
C3: B3 COUNTA
C5: What are we doing here?
C6: We're going to take a look at CountA.
C7: It counts the number of non-blank value. So easy! No need to even practice!
C9: This is amazing! What if I want to do more?
C10: Google countA, I guess? Or look at the different kinds of counts.
C12: How do I get started again?
C13: This example is ready to go, just keep reading!
A16: * | B16: INSTRUCTIONS
B17: CountA just counts the number of non-blanks. That's it. Short and sweet! Great for data quality control.
A19: * | B19: CountA example
B20: I have | C20: Two blanks | D20: Everything
D21: is good
B22: a blank | D22: no blanks
B23: four rows | C23: Three rows | D23: Five rows
B24: with data | C24: with data | D24: with data
B26: =COUNTA(B20:B24) | C26: =COUNTA(C20:C24) | D26: =COUNTA(D20:D24)
B27: =COUNTA(B20:B24) -> 4 | C27: =COUNTA(C20:C24) -> 3 | D27: =COUNTA(D20:D24) -> 5
A29: * | B29: SUPPLEMENTARY INFORMATION
A31: * | B31: Spaces
B33: If CountA is returning a number higher than you were expecting, it could be that one of the cells contains a space instead of a blank.
B34: Try using find/replace (see A5) and matching the whole cell content to find spaces and replacing them with nothing.
B36: There is
B38: a space in B37
B39: so it's counting
B40: 5 non-blank rows
B42: =COUNTA(B36:B40)
B43: =COUNTA(B36:B40) -> 5

Sheet B4 Instructions
A1: * | B1: Main Menu | C1: Exercise | D1: Data worksheet
C3: B4 SUMIF AND SUMIFS
C5: What are we doing here?
C6: We're going to learn about SumIF and SumIFs.
C7: These let us use criteria in order to add numbers.
C9: This is amazing! What if I want to do more?
C10: I'm not sure! Maybe learn about CSE formulas in 2_2?
C12: How do I get started again?
C13: This example is ready to go, just keep reading!
C14: Once you think you understand, go do the exercise!
A17: * | B17: INSTRUCTIONS
B18: Both SumIF and SumIFs use ranges, and you're going to want to use the $ symbol for those so that the ranges will stay the same no matter where you
B19: move in the worksheet.
B21: SumIF has three arguments. First, give it the range of cells in which it is going to lookup a value that will fulfill your desired criteria.
B22: Next, give it your criteria so that it can search in the provided range and see if anything fits your criteria.
B23: Lastly, tell it what it is adding up.
B25: SumIFs needs at least three arguments. First, give it the range of cells that it is going to add.
B26: Next, give it the range where you are going to check a criteria.
B27: Lastly, tell it what criteria it needs to check.
B28: You can repeat the second and third steps for other criteria to check IN OTHER COLUMNS. SumIFs does not understand 'OR' logic, you can't check
B29: for more than one criteria in a same column (or at least, not without involving brain breaking arrays or adding SumIFs together).
A31: * | B31: SumIF Example
A33: * | B33: Tool cost table
B34: Status | C34: Name | D34: Tool | E34: Cost | F34: <- Try changing the costs and
B35: Hero | C35: Peter Parker | D35: Web Slinger | E35: 24.85 | F35: see what happens to the totals below
B36: Hero | C36: Bruce Wayne | D36: Bat car | E36: 125030
B37: Villain | C37: Dr. Horrible | D37: Freeze Ray | E37: 350000
B38: Hero | C38: Peter Parker | D38: Venom antidote | E38: 55.82
B39: Ambiguous | C39: Dentists | D39: Scary looking equipment | E39: 552.25
A41: * | B41: ="Adding up the cost of tools for everyone with a " &B44& " status!" -> Adding up the cost of tools for everyone with a Hero status!
B42: Try changing "Hero" to "Villain" or "Ambiguous" and see what happens!
B43: Criteria | C43: Sum of cost of tools | D43: Text of formula
B44: Hero | C44: =SUMIF($B$35:$B$39,B44,$E$35:$E$39) -> 125110.67 | D44: =SUMIF($B$35:$B$39,B44,$E$35:$E$39)
A46: * | B46: ="Adding up the cost of tools for everyone who is a "&B49&" OR " &B50 & " - 2 possibilities in a same column!" -> Adding up the cost of tools for everyone who is a Hero OR Ambiguous - 2 possibilities in a same column!
B47: Try changing the criteria in the first column and see what happens!
B48: Criteria | C48: Sum of cost of tools | D48: Text of formula
B49: Hero | C49: =SUMIF($B$35:$B$39,B49,$E$35:$E$39)+SUMIF($B$35:$B$39,B50,$E$35:$E$39) -> 125662.92 | D49: =SUMIF($B$35:$B$39,B49,$E$35:$E$39)+SUMIF($B$35:$B$39,B50,$E$35:$E$39)
B50: Ambiguous
A52: * | B52: SumIFs Example
A54: * | B54: Coolness and annual salary table
B55: Status | C55: Name | D55: Coolness | E55: Annual salary | F55: <- Try changing the salaries and
B56: Hero | C56: Peter Parker | D56: Cool | E56: 45000 | F56: see what happens to the totals below
B57: Hero | C57: Bruce Wayne | D57: Super cool | E57: 2999999
B58: Villain | C58: Dr. Horrible | D58: Super cool | E58: 15000
B59: Hero | C59: Ted Parker | D59: Cool | E59: 125000
B60: Ambiguous | C60: Daredevil | D60: Super cool | E60: 10000
A62: * | B62: ="Adding up the salary of everyone with the " &B65 &" status!" -> Adding up the salary of everyone with the Hero status!
B63: Try changing "Hero" to "Villain" or "Ambiguous" and see what happens!
B64: Criteria | C64: Sum of salaries | D64: Text of formula
B65: Hero | C65: =SUMIFS($E$56:$E$60,$B$56:$B$60,B65) -> 3169999 | D65: =SUMIFS($E$56:$E$60,$B$56:$B$60,B65)
A67: * | B67: ="Adding up the salary of every "&B71& " " &B70 & " - criteria over two different columns!" -> Adding up the salary of every Super cool Hero - criteria over two different columns!
B68: Try changing the criteria in the first column and see what happens!
B69: Criteria | C69: Sum of cost of tools | D69: Text of formula
B70: Hero | C70: =SUMIFS($E$56:$E$60,$B$56:$B$60,B70,$D$56:$D$60,B71) -> 2999999 | D70: SUMIFS($E$56:$E$60,$B$56:$B$60,B70,$D$56:$D$60,B71)
B71: Super cool
A73: * | B73: SUPPLEMENTARY INFORMATION
A75: * | B75: Important difference between SumIF and SumIFs
B77: The first argument in SumIF is the range containing the criteria, while the first argument in SumIFs is the range to add up together.
A79: * | B79: In-depth look at the SumIFs formula
B80: =SUMIFS($E$56:$E$60,$B$56:$B$60,B70,$D$56:$D$60,B71)
B81: Sure, this formula entered in cell C70 looks like a lot of gibberish, until you remember to look for the comma "," which separates the arguments. | C81: In the first part, $E$56:$E$60, we tell Excel that we want to add numbers in the last column (column E) of the coolness and annual salary table. | D81: Next, we tell Excel where to look for a criteria in the table. We want it to look at the "Status" column (column B) that identifies heroes and villains in the "Coolness" table: $B$56:$B$60 | E81: We then want Excel to check the contents of that column against our desired criteria. Here, we've given it B70, the address of a cell that contains "Hero" or "Villain" or "Ambiguous". | F81: Rinse and repeat for the next criteria! We look in the "Coolness" column (column D - $D$56:$D$60) and check the coolness against our desired criteria in cell B71.
B83: The "$" sign is used for absolute referencing. It mean that if we copy-paste this formula elsewhere, it is still going to look at the exact same range/table.
B84: When entering a formula, highlight an argument and hit F4 on your keyboard to quickly toggle on absolute referencing.

Sheet B4 Exercise
A1: * | B1: Main Menu | C1: Instructions | D1: Data worksheet | I1: CD | J1: SUB | K1: SUBDIV Name | L1: Tot Pop 2021 | N1: Unique CD
I2: 5 | J2: 1 | K2: Barrington | L2: 6523 | N2: 5
A3: * | B3: SUMIF AND SUMIFS EXERCISE | I3: 1 | J3: 4 | K3: Clark's Harbour | L3: 725 | N3: 1
B4: We're going to estimate the total population (contained in column E of the 2021 CSD worksheet) for each census division in NS. | I4: 1 | J4: 6 | K4: Shelburne | L4: 4336 | N4: 2
B5: You'll notice that census divisions appear more than once in the 2021 CSD worksheet. | I5: 1 | J5: 8 | K5: Shelburne | L5: 1644 | N5: 3
I6: 1 | J6: 9 | K6: Lockeport | L6: 476 | N6: 4
B7: First of all, I've prepared a lot of things for you, using concepts we've already covered: | I7: 2 | J7: 1 | K7: Argyle | L7: 7870 | N7: 6
B8: 1 - I've copied columns B, C, D and E of the 2021 CSD worksheet into columns H, I, J, and K of this worksheet. | I8: 2 | J8: 4 | K8: Yarmouth | L8: 10067 | N8: 7
B9: 2 - I changed a "1" CD to a "5" (in H2) for the purposes of making sure that you are using absolute addresses in your ranges | I9: 2 | J9: 6 | K9: Yarmouth | L9: 6829 | N9: 8
B10: and to illustrate that content in columns does not need to be in order... | I10: 2 | J10: 40 | K10: Yarmouth 33 | L10: 181 | N10: 9
B11: 3 - I've copied-pasted column H into column M. | I11: 3 | J11: 1 | K11: Clare | L11: 7678 | N11: 10
B12: 4 - I removed duplicates from column M. | I12: 3 | J12: 4 | K12: Digby | L12: 7242 | N12: 11
B13: 5 - I copy-pasted column M into the exercise's column B below. | I13: 3 | J13: 6 | K13: Digby | L13: 2001 | N13: 12
I14: 3 | J14: 9 | K14: Bear River (Part) 6 | L14: 141 | N14: 13
B15: Now, I trust YOU to enter a formula in column C that will use SumIF and the values in column B to find the total population | I15: 4 | J15: 1 | K15: Medway River 11 | L15: 15 | N15: 14
B16: (column K) by census division according to the 2021 CSD worksheet. And do the same in column D for SumIFs. | I16: 4 | J16: 9 | K16: Ponhook Lake 10 | L16: 15 | N16: 15
B17: There are 96 rows in column I: row 1 has the header, and rows 2 to 96 contain data. | I17: 4 | J17: 10 | K17: Queens | L17: 10422 | N17: 16
I18: 4 | J18: 15 | K18: Wildcat 12 | L18: 49 | N18: 17
A19: * | B19: Table to use to practice SumIF and SumIFs | G19: Did it work? | I19: 5 | J19: 1 | K19: Annapolis, Subd. D | L19: 3049 | N19: 18
B20: Census Division | C20: SumIf TotPop | D20: SumIfs TotPop | E20: Expected result | G20: Success? | I20: 5 | J20: 2 | K20: Bear River (Part) 6 | L20: 0
B21: 1 | E21: 7181 | G21: =IF(AND(E21=C21, E21=D21),"WOOHOO!","Not yet…") -> Not yet… | I21: 5 | J21: 4 | K21: Annapolis, Subd. A | L21: 5980
B22: 2 | E22: 24947 | G22: =IF(AND(E22=C22, E22=D22),"WOOHOO!","Not yet…") -> Not yet… | I22: 5 | J22: 6 | K22: Bear River 6B | L22: 15
B23: 3 | E23: 17062 | G23: =IF(AND(E23=C23, E23=D23),"WOOHOO!","Not yet…") -> Not yet… | I23: 5 | J23: 8 | K23: Annapolis Royal | L23: 530
B24: 4 | E24: 10501 | G24: =IF(AND(E24=C24, E24=D24),"WOOHOO!","Not yet…") -> Not yet… | I24: 5 | J24: 9 | K24: Annapolis, Subd. B | L24: 4587
B25: 5 | E25: 27775 | G25: =IF(AND(E25=C25, E25=D25),"WOOHOO!","Not yet…") -> Not yet… | I25: 5 | J25: 14 | K25: Annapolis, Subd. C | L25: 5218
B26: 6 | E26: 48599 | G26: =IF(AND(E26=C26, E26=D26),"WOOHOO!","Not yet…") -> Not yet… | I26: 5 | J26: 16 | K26: Middleton | L26: 1873
B27: 7 | E27: 62914 | G27: =IF(AND(E27=C27, E27=D27),"WOOHOO!","Not yet…") -> Not yet… | I27: 6 | J27: 1 | K27: Lunenburg | L27: 25545
B28: 8 | E28: 45140 | G28: =IF(AND(E28=C28, E28=D28),"WOOHOO!","Not yet…") -> Not yet… | I28: 6 | J28: 4 | K28: Bridgewater | L28: 8790
B29: 9 | E29: 440072 | G29: =IF(AND(E29=C29, E29=D29),"WOOHOO!","Not yet…") -> Not yet… | I29: 6 | J29: 6 | K29: Lunenburg | L29: 2396
B30: 10 | E30: 51476 | G30: =IF(AND(E30=C30, E30=D30),"WOOHOO!","Not yet…") -> Not yet… | I30: 6 | J30: 8 | K30: Mahone Bay | L30: 1064
B31: 11 | E31: 30538 | G31: =IF(AND(E31=C31, E31=D31),"WOOHOO!","Not yet…") -> Not yet… | I31: 6 | J31: 9 | K31: Chester | L31: 10693
B32: 12 | E32: 43657 | G32: =IF(AND(E32=C32, E32=D32),"WOOHOO!","Not yet…") -> Not yet… | I32: 6 | J32: 11 | K32: Gold River 21 | L32: 81
... B38: 18 | E38: 7441 | G38: =IF(AND(E38=C38, E38=D38),"WOOHOO!","Not yet…") -> Not yet… | I38: 7 | J38: 12 | K38: Kentville | L38: 6630
I39: 7 | J39: 2 | K39: Annapolis Valley First Nation | L39: 743
I40: 7 | J40: 16 | K40: Kings, Subd. B | L40: 11951
I41: 7 | J41: 21 | K41: Kings, Subd. D | L41: 5264
I42: 7 | J42: 24 | K42: Wolfville | L42: 5057
I43: 7 | J43: 27 | K43: Glooscap 35 | L43: 111
I44: 8 | J44: 3 | K44: West Hants | L44: 19509
I45: 8 | J45: 8 | K45: East Hants | L45: 22892
I46: 8 | J46: 14 | K46: Indian Brook 14 | L46: 2739
I47: 9 | J47: 19 | K47: Cole Harbour 30 | L47: 208
I48: 9 | J48: 34 | K48: Halifax | L48: 439819
I49: 9 | J49: 37 | K49: Beaver Lake 17 | L49: 20
I50: 9 | J50: 38 | K50: Sheet Harbour 36 | L50: 10
... I96: 18 | J96: 6 | K96: Victoria, Subd. A | L96: 2673

Sheet C1 Instructions
A1: * | B1: Main Menu | C1: Exercise | D1: Data worksheet
C3: C1 CONCATENATION
C5: What are we doing here?
C6: We're going to use & to concatenate some strings/text
C8: This is amazing! What if I want to learn more?
C9: Just Google "Excel string functions"
C11: How do I get started again?
C12: This example is ready to go, just keep reading!
C13: Once you think you understand, go do the exercise!
A16: * | B16: INSTRUCTIONS
B17: Use the & operator to concatenate text, just like you would use + or - to add or substract numbers. Use the address of a cell to concatenate its contents.
B18: If the cell contains a number, it will be converted to text. Use "" to insert text.
B19: Use """ to insert the " symbol, look carefully at the formula that results. (In macros, we use "" for some reason, but you don't need to know that right now)
B20: Notice that only the result displayed by cells with formulas is concatenated, not the formula itself.
A22: * | B22: Data | C22: Formulas using data
A24: * | B24: Let's concatenate the content of cells B25 to B29
B25: Use & to concatenate. | C25: =B25&B26&B27&B28&B29
B26: Use the address of a cell to concatenate it. | C26: =B25&B26&B27&B28&B29 -> Use & to concatenate.Use the address of a cell to concatenate it.If the cell contains a number, it will be converted to text.26is a number.
B27: If the cell contains a number, it will be converted to text.
B28: 26
B29: is a number.
A31: * | B31: Let's insert some text and spaces to the content of cells B32 and B33
B32: Use "" to insert text. | C32: ="Text inserted. "&B32&" "&B33
B33: Wow there are spaces! | C33: ="Text inserted. "&B32&" "&B33 -> Text inserted. Use "" to insert text. Wow there are spaces!
A35: * | B35: Let's insert "Wow!" and the contents of B36 and B37
B36: Use """ to insert the " symbol, | C36: ="""Wow!"" "&B36&B37
B37: look carefully at the resulting formula | C37: ="""Wow!"" "&B36&B37 -> "Wow!" Use """ to insert the " symbol, look carefully at the resulting formula
A39: * | B39: Let's insert C37 and the contents of B41
C40: =B41&" "&C37
B41: Notice that the content displayed by cells with formulas is concatenated, not the formula itself. | C41: =B41&" "&C37 -> Notice that the content displayed by cells with formulas is concatenated, not the formula itself. "Wow!" Use """ to insert the " symbol, look carefully at the resulting formula
A43: * | B43: SUPPLEMENTARY INFORMATION
A45: * | B45: Recent versions of Excel will allow you to use the TEXTJOIN formula to concatenate text strings with a delimiter
B46: Use & to concatenate. | C46: =TEXTJOIN(" ",TRUE,B46:B47)
B47: Use the address of a cell to concatenate it. | C47: =_xlfn.TEXTJOIN(" ",TRUE,B46:B47) -> Use & to concatenate. Use the address of a cell to concatenate it.
B49: If cell C47 doesn't seem to display the concatenated version of B45 and B46 with a text in between, you might not have the right version of Excel.
B50: TEXTOIN is a great option when everything needs to be concatenated with the same delimiter.
A52: * | B52: Recent versions of Excel will allow you to use the CONCAT formula to concatenate text strings
B53: Use & to concatenate. | C53: =CONCAT(B53:B54)
B54: Use the address of a cell to concatenate it. | C54: =_xlfn.CONCAT(B53:B54) -> Use & to concatenate.Use the address of a cell to concatenate it.
B56: This is very similar to using the & symbol to concatenate.
B57: If you want to concatenate several cells in a range, you might find it easier to add a space or delimiter directly in the cells to concatenate.
A59: * | B59: Recent versions of Excel also allow you to concatenate text with flash fill
B60: Google "Flash fill Excel" to find out more.
B62: Flash fill will work best if there's a common pattern to how you want to concatenate cells.
B63: Just like other methods here, it can concatenate across multiple columns (or rows)
B64: However, it will not update itself dynamically, which means that flash fill is best used when no more modifications will be made to a spreadsheet.

Sheet C1 Exercise
A1: * | B1: Main Menu | C1: Instructions | D1: Data worksheet
A3: * | B3: CONCATENATION EXERCISE
B4: The 2021 CSD worksheet contains Nova Scotia data from the 2021 census. You get confused when you try to make sense of the geography, so you
B5: decide you want to create a single column containing the abbreviation "NS", the number of the census division (CD column), and the number of
B6: the subdivision (SUBDIV column) separated by a "-" . Use concatenation in order to achieve this. See the expected results column to get an idea
B7: of what your concatenated string should look like.
B9: You don't need to transfer any data to this worksheet in order for the concatenation to work. You can just select the cell in the other worksheet
B10: when typing in your formula, or reference it using the provided example. But I'm in a good mood, so I've gone ahead and copied the data over to
B11: this worksheet in columns E and F
A13: * | B13: Referencing cell A2 in the 2021 CSD worksheet
A15: * | B15: Typing in | C15: Results in the number
B16: ='2021 CSD'!A2 | C16: ='2021 CSD'!A2 -> 12
A18: * | B18: Table to use to practice concatenation | H18: Did it work?
A19: * | B19: Row in 2021 CSD | C19: Insert your formula in this column | D19: Expected result | E19: CD | F19: SUBDIV | H19: Success?
B20: 2 | D20: NS 1-1 | E20: 1 | F20: 1 | H20: =IF(D20=C20,"YAY!","Not yet...") -> Not yet...
B21: 3 | D21: NS 1-4 | E21: 1 | F21: 4 | H21: =IF(D21=C21,"YAY!","Not yet...") -> Not yet...
B22: 4 | D22: NS 1-6 | E22: 1 | F22: 6 | H22: =IF(D22=C22,"YAY!","Not yet...") -> Not yet...
B23: 5 | D23: NS 1-8 | E23: 1 | F23: 8 | H23: =IF(D23=C23,"YAY!","Not yet...") -> Not yet...
B24: 6 | D24: NS 1-9 | E24: 1 | F24: 9 | H24: =IF(D24=C24,"YAY!","Not yet...") -> Not yet...
B25: 7 | D25: NS 2-1 | E25: 2 | F25: 1 | H25: =IF(D25=C25,"YAY!","Not yet...") -> Not yet...
B26: 8 | D26: NS 2-4 | E26: 2 | F26: 4 | H26: =IF(D26=C26,"YAY!","Not yet...") -> Not yet...
B27: 9 | D27: NS 2-6 | E27: 2 | F27: 6 | H27: =IF(D27=C27,"YAY!","Not yet...") -> Not yet...
B28: 10 | D28: NS 2-40 | E28: 2 | F28: 40 | H28: =IF(D28=C28,"YAY!","Not yet...") -> Not yet...
B29: 11 | D29: NS 3-1 | E29: 3 | F29: 1 | H29: =IF(D29=C29,"YAY!","Not yet...") -> Not yet...
B30: 12 | D30: NS 3-4 | E30: 3 | F30: 4 | H30: =IF(D30=C30,"YAY!","Not yet...") -> Not yet...
B31: 13 | D31: NS 3-6 | E31: 3 | F31: 6 | H31: =IF(D31=C31,"YAY!","Not yet...") -> Not yet...
B32: 14 | D32: NS 3-9 | E32: 3 | F32: 9 | H32: =IF(D32=C32,"YAY!","Not yet...") -> Not yet...

Sheet C2 Instructions
A1: * | B1: Main Menu | C1: Exercise | D1: Data worksheet
C3: C2 LEFT, RIGHT, MID, and FIND STRING FUNCTIONS
C5: What are we doing here?
C6: We're going to extract parts of the text contained in a cell.
C7: This is REALLY useful!
C9: This is amazing! What if I want to do more?
C10: Just Google "Excel string functions"
C12: How do I get started again?
C13: This example is ready to go, just keep reading!
C14: Once you think you understand, go do the exercise!
A17: * | B17: INSTRUCTIONS
B18: The LEFT function will extract a specified number of characters starting from the left of a string. Don't worry, both text and numbers can be manipulated as strings.
B19: The RIGHT function does the same thing, but it starts from the right.
B20: The MID function lets you extract a specified number of characters, starting from a specified location.
B21: The FIND function will try to find a character, and give you the number of its position in a string. We use it to do MAGIC!
A23: * | B23: Data | C23: Lets use LEFT to extract the province | D23: Let's use RIGHT to extract the last number
C24: =LEFT(B25,2) | D24: =RIGHT(B25,1)
B25: NS 1-8 | C25: =LEFT(B25,2) -> NS | D25: =RIGHT(B25,1) -> 8
B26: NS 2-4 | C26: =LEFT(B26,2) -> NS | D26: =RIGHT(B26,1) -> 4
B27: NS 2-40 | C27: =LEFT(B27,2) -> NS | D27: =RIGHT(B27,1) -> 0
B28: NS 3-1 | C28: =LEFT(B28,2) -> NS | D28: =RIGHT(B28,1) -> 1
B29: NS 3-9 | C29: =LEFT(B29,2) -> NS | D29: =RIGHT(B29,1) -> 9
B30: NS 4-10 | C30: =LEFT(B30,2) -> NS | D30: =RIGHT(B30,1) -> 0
B31: QC 26-3 | C31: =LEFT(B31,2) -> QC | D31: =RIGHT(B31,1) -> 3
B32: ON 8-446 | C32: =LEFT(B32,2) -> ON | D32: =RIGHT(B32,1) -> 6
A34: * | B34: Data | C34: Let's use MID to grab the 3 characters following the space | D34: Let's see what FIND does when we search for "-"
C35: =MID(B36,4,3) | D35: =FIND("-",B36) | E35: Counting from the left, that's the number of characters until we get to "-"
B36: NS 1-8 | C36: =MID(B36,4,3) -> 1-8 | D36: =FIND("-",B36) -> 5
B37: NS 2-4 | C37: =MID(B37,4,3) -> 2-4 | D37: =FIND("-",B37) -> 5
B38: NS 2-40 | C38: =MID(B38,4,3) -> 2-4 | D38: =FIND("-",B38) -> 5
B39: NS 3-1 | C39: =MID(B39,4,3) -> 3-1 | D39: =FIND("-",B39) -> 5
B40: NS 3-9 | C40: =MID(B40,4,3) -> 3-9 | D40: =FIND("-",B40) -> 5
B41: NS 4-10 | C41: =MID(B41,4,3) -> 4-1 | D41: =FIND("-",B41) -> 5
B42: QC 26-3 | C42: =MID(B42,4,3) -> 26- | D42: =FIND("-",B42) -> 6
B43: ON 8-446 | C43: =MID(B43,4,3) -> 8-4 | D43: =FIND("-",B43) -> 5
A45: * | B45: Data | C45: Let's use MID and FIND to grab the number in the middle | D45: Let's use RIGHT and FIND to grab the number on the right
C46: =MID(B47,4,(FIND("-",B47)-4)) | D46: =RIGHT(B47,(LEN(B47)-FIND("-",B47))) | E46: LEN gives you the total number of characters in a string, by the way.
B47: NS 1-8 | C47: =MID(B47,4,(FIND("-",B47)-4)) -> 1 | D47: =RIGHT(B47,(LEN(B47)-FIND("-",B47))) -> 8 | E47: Congrats on finding the hidden bonus function!
B48: NS 2-4 | C48: =MID(B48,4,(FIND("-",B48)-4)) -> 2 | D48: =RIGHT(B48,(LEN(B48)-FIND("-",B48))) -> 4
B49: NS 2-40 | C49: =MID(B49,4,(FIND("-",B49)-4)) -> 2 | D49: =RIGHT(B49,(LEN(B49)-FIND("-",B49))) -> 40
B50: NS 3-1 | C50: =MID(B50,4,(FIND("-",B50)-4)) -> 3 | D50: =RIGHT(B50,(LEN(B50)-FIND("-",B50))) -> 1
B51: NS 3-9 | C51: =MID(B51,4,(FIND("-",B51)-4)) -> 3 | D51: =RIGHT(B51,(LEN(B51)-FIND("-",B51))) -> 9
B52: NS 4-10 | C52: =MID(B52,4,(FIND("-",B52)-4)) -> 4 | D52: =RIGHT(B52,(LEN(B52)-FIND("-",B52))) -> 10
B53: QC 26-3 | C53: =MID(B53,4,(FIND("-",B53)-4)) -> 26 | D53: =RIGHT(B53,(LEN(B53)-FIND("-",B53))) -> 3
B54: ON 8-446 | C54: =MID(B54,4,(FIND("-",B54)-4)) -> 8 | D54: =RIGHT(B54,(LEN(B54)-FIND("-",B54))) -> 446
A56: * | B56: SUPPLEMENTARY INFORMATION
A58: * | B58: In-depth look at the MID formula and embedded formulas
B59: =MID(B47,4,(FIND("-",B47)-4))
B60: To figure out what the heck is happening in a formula, look for the comma "," which separates the arguments. | C60: Here, we use MID, then we look at text in a cell, then we give the number of characters from which to start the extraction, then we give the number of characters to extract. To do that last part, we use FIND, which itself will look for a symbol "-" in a given cell (B47). | D60: So that last part,(FIND("-",B47)-4) goes together. It uses FIND to find the number associated with the "-" symbol in cell B47 then subtracts 4. That gives us the number of characters to extract before we hit the "-" symbol. | E60: I could have made this example even more complicated by using the FIND formula to return the number associated to the space after the province, using that as the number from which to start the extraction, and than using it again when it comes time to subtract.
A62: * | B62: Recent versions of Excel also allow you to split text with flash fill
B63: Google "Flash fill Excel" to find out more.
B65: Flash fill will work best if there's a common pattern to how you want to split your cells.
B66: However, it will not update itself dynamically, which means that flash fill is best used when no more modifications will be made to a spreadsheet.
A68: * | B68: Look into Text to Columns
B69: Google "Text to Columns" to find out more.
B71: Text to columns can split your text at a given delimiter.
B72: However, it will overwrite columns to the right of your initial column, so use carefully!

Sheet C2 Exercise
A1: * | B1: Main Menu | C1: Instructions | D1: Data worksheet
A3: * | B3: LEFT, RIGHT, MID, FIND, LEN EXERCISE
B4: This exercise is harder than it looks, but I believe in you!
B5: Scroll down and look at that list of names.
B6: Figure out a way to extract the first name and the last name using a formula.
B7: Now you'll be able to alphabetize the list by last name!
A9: * | B9: Table with names to extract | F9: Example of a list sorted by last name
B10: Names | C10: First Name | D10: Last Name | F10: Do the exercise and ordering by last name becomes very easy to do!
B11: Barbara Gordon | F11: Brown Stephanie
B12: Bruce Wayne | F12: Cain Cassandra
B13: Cassandra Cain | F13: Drake Tim
B14: Damian Wayne | F14: Gordon Barbara
B15: Helena Rosa Bertinelli | F15: Harper Roy
B16: Jason Todd | F16: John Grayson Richard
B17: Richard John Grayson | F17: Kyle Selina
B18: Roy Harper | F18: Rosa Bertinelli Helena
B19: Selina Kyle | F19: Todd Jason
B20: Stephanie Brown | F20: Wayne Bruce
B21: Tim Drake | F21: Wayne Damian

Sheet C3 Instructions
A1: * | B1: Main Menu | C1: Exercise
C3: C3 VLOOKUP
C5: What are we doing here?
C6: Vlookup is fun. It'll go look up stuff for you. You like having fun, right?
C8: This is amazing! What if I want to do more?
C9: You could also try Hlookup and in recent versions of Excel, Xlookup.
C10: Google wildcards in Vlookup. And learn about TRIM (important).
C11: When you're feeling confident in your skills, Google 'Excel' and 'Index Match'
C13: How do I get started again?
C14: This example is ready to go, just keep reading!
C15: If you need a reset, copy-paste the table at the bottom of this worksheet
C16: Once you think you understand, go do the easiest exercise yet!
A19: * | B19: INSTRUCTIONS
B20: Vlookup will put data in your cell by looking up values in another column. It has four arguments.
B21: First, it needs to know what it will be looking up.
B22: Second, it wants to know the range in which it will be looking up whatever it is you need it to look up.
B23: Third, it wants the number of the column in the range from which it will be extracting data.
B24: Lastly, it wants to know if you need an exact match or not. "FALSE" is almost always the option you want to use here.
B26: Whenever you're working with ranges or arrays, it's usually a good idea to use the "$" symbols.
B27: And keep in mind that Vlookup never worries about capitalization.
B29: In the examples below, we have a nice table of sounds that animals make…
B30: …while Farmer Ted has a list of animals for which he would like to automatically associate sounds.
A32: * | B32: Simple Vlookup example and error handling
A34: * | B34: Table of animals and the sounds that they make | E34: Farmer Ted's list of animals | G34: Simple Vlookup | H34: Error handling
B35: Animals | C35: Sounds | E35: Animal Names | F35: Animals | G35: =VLOOKUP(F36,$B$36:$C$42,2,FALSE) | H35: =IFERROR(VLOOKUP(F36,$B$36:$C$42,2,FALSE),"NOT FOUND!!!")
B36: Cat | C36: Miow | E36: Felix | F36: Cat | G36: =VLOOKUP(F36,$B$36:$C$42,2,FALSE) -> Miow | H36: =IFERROR(VLOOKUP(F36,$B$36:$C$42,2,FALSE),"NOT FOUND!!!") -> Miow
B37: Giraffe | C37: ??? | E37: Spot | F37: Dog | G37: =VLOOKUP(F37,$B$36:$C$42,2,FALSE) -> Woof | H37: =IFERROR(VLOOKUP(F37,$B$36:$C$42,2,FALSE),"NOT FOUND!!!") -> Woof
B38: Cricket | C38: Cricket cricket | E38: Hortense | F38: Giraffe | G38: =VLOOKUP(F38,$B$36:$C$42,2,FALSE) -> ??? | H38: =IFERROR(VLOOKUP(F38,$B$36:$C$42,2,FALSE),"NOT FOUND!!!") -> ???
B39: Cow | C39: Mooo | E39: Rover | F39: Dog | G39: =VLOOKUP(F39,$B$36:$C$42,2,FALSE) -> Woof | H39: =IFERROR(VLOOKUP(F39,$B$36:$C$42,2,FALSE),"NOT FOUND!!!") -> Woof
B40: Pig | C40: Oink oink | E40: Bacon | F40: Pig | G40: =VLOOKUP(F40,$B$36:$C$42,2,FALSE) -> Oink oink | H40: =IFERROR(VLOOKUP(F40,$B$36:$C$42,2,FALSE),"NOT FOUND!!!") -> Oink oink
B41: Duck | C41: Quack quack | E41: Donald | F41: Duck | G41: =VLOOKUP(F41,$B$36:$C$42,2,FALSE) -> Quack quack | H41: =IFERROR(VLOOKUP(F41,$B$36:$C$42,2,FALSE),"NOT FOUND!!!") -> Quack quack
B42: Dog | C42: Woof | E42: Jimmy | F42: Cricket | G42: =VLOOKUP(F42,$B$36:$C$42,2,FALSE) -> Cricket cricket | H42: =IFERROR(VLOOKUP(F42,$B$36:$C$42,2,FALSE),"NOT FOUND!!!") -> Cricket cricket
E43: Barbecued | F43: Pig | G43: =VLOOKUP(F43,$B$36:$C$42,2,FALSE) -> Oink oink | H43: =IFERROR(VLOOKUP(F43,$B$36:$C$42,2,FALSE),"NOT FOUND!!!") -> Oink oink
D44: No Gators in table of animals -> | E44: Later | F44: Gator | G44: =VLOOKUP(F44,$B$36:$C$42,2,FALSE) -> #N/A | H44: =IFERROR(VLOOKUP(F44,$B$36:$C$42,2,FALSE),"NOT FOUND!!!") -> NOT FOUND!!!
E45: Tournedos | F45: Pig | G45: =VLOOKUP(F45,$B$36:$C$42,2,FALSE) -> Oink oink | H45: =IFERROR(VLOOKUP(F45,$B$36:$C$42,2,FALSE),"NOT FOUND!!!") -> Oink oink
E46: Soushi | F46: Cat | G46: =VLOOKUP(F46,$B$36:$C$42,2,FALSE) -> Miow | H46: =IFERROR(VLOOKUP(F46,$B$36:$C$42,2,FALSE),"NOT FOUND!!!") -> Miow
A48: * | B48: SUPPLEMENTARY INFORMATION
A50: * | B50: In-depth look at the Vlookup formula
B51: =vlookup(F46,$B$36:$C$42,2,False)
B52: First, we tell Excel we want to lookup "Cat" or whatever is contained in cell F46.
B53: Second, we tell Excel we'll be looking that up in our table of animal sounds, in a range, B36 to C42 ($B$36:$C$42).
B54: Third, the number "2" tells Excel that what we want to retrieve is the content of the second column in our range.
B55: Animals are in the first column, sounds in the second column. So look for "Cat", and tell us what sound the "cat" makes.
B56: Fourth "False" tells Excel that we want an exact match.
A58: * | B58: Handling error messages
B59: When Vlookup can't find what it's looking for, it returns an error message #N/A. You'll notice above that this happened to Later the Gator in
B60: cell G44. This is really annoying when trying to analyze your data - the error propates to your various formulas. If you want, you can encapsulate
B61: Vlookup inside the IfError formula to return a message saying that the value was not found instead. Look at 2_5 if you want to learn a bit more
B62: about using IF logic in your formulas.
A64: * | B64: INSTRUCTIONS
B65: Vlookup also works with wildcards. Like "*" & F71 & "*". Um…just…look at the example, I guess.
A67: * | B67: Vlookup with wildcards
A69: * | B69: Table of animals and the sounds that they make | E69: Farmer Ted's list of animals | G69: Simple Vlookup | H69: With Wildcards
B70: Fuzzy animals - Exact matches won't work | C70: Sounds | E70: Animal Names | F70: Animals | G70: =VLOOKUP(F71,$B$71:$C$77,2,FALSE) | H70: =VLOOKUP("*"&F71&"*",$B$71:$C$77,2,FALSE)
B71: A cat | C71: Miow | E71: Felix | F71: Cat | G71: =VLOOKUP(F71,$B$71:$C$77,2,FALSE) -> #N/A | H71: =VLOOKUP("*" & F71 & "*",$B$71:$C$77,2,FALSE) -> Miow
B72: The giraffe | C72: ??? | E72: Spot | F72: Dog | G72: =VLOOKUP(F72,$B$71:$C$77,2,FALSE) -> #N/A | H72: =VLOOKUP("*" & F72 & "*",$B$71:$C$77,2,FALSE) -> Woof
B73: Cricket Cricket | C73: Cricket cricket | E73: Hortense | F73: Giraffe | G73: =VLOOKUP(F73,$B$71:$C$77,2,FALSE) -> #N/A | H73: =VLOOKUP("*" & F73 & "*",$B$71:$C$77,2,FALSE) -> ???
B74: Wow Cow | C74: Mooo | E74: Rover | F74: Dog | G74: =VLOOKUP(F74,$B$71:$C$77,2,FALSE) -> #N/A | H74: =VLOOKUP("*" & F74 & "*",$B$71:$C$77,2,FALSE) -> Woof
B75: Big pig | C75: Oink oink | E75: Bacon | F75: Pig | G75: =VLOOKUP(F75,$B$71:$C$77,2,FALSE) -> #N/A | H75: =VLOOKUP("*" & F75 & "*",$B$71:$C$77,2,FALSE) -> Oink oink
B76: Duck goose | C76: Quack quack | E76: Donald | F76: Duck | G76: =VLOOKUP(F76,$B$71:$C$77,2,FALSE) -> #N/A | H76: =VLOOKUP("*" & F76 & "*",$B$71:$C$77,2,FALSE) -> Quack quack
B77: Wow dog wow | C77: Woof | E77: Jimmy | F77: Cricket | G77: =VLOOKUP(F77,$B$71:$C$77,2,FALSE) -> #N/A | H77: =VLOOKUP("*" & F77 & "*",$B$71:$C$77,2,FALSE) -> Cricket cricket
E78: Barbecued | F78: Pig | G78: =VLOOKUP(F78,$B$71:$C$77,2,FALSE) -> #N/A | H78: =VLOOKUP("*" & F78 & "*",$B$71:$C$77,2,FALSE) -> Oink oink
D79: No Gators in table of animals -> | E79: Later | F79: Gator | G79: =VLOOKUP(F79,$B$71:$C$77,2,FALSE) -> #N/A | H79: =VLOOKUP("*" & F79 & "*",$B$71:$C$77,2,FALSE) -> #N/A
E80: Tournedos | F80: Pig | G80: =VLOOKUP(F80,$B$71:$C$77,2,FALSE) -> #N/A | H80: =VLOOKUP("*" & F80 & "*",$B$71:$C$77,2,FALSE) -> Oink oink
E81: Soushi | F81: Cat | G81: =VLOOKUP(F81,$B$71:$C$77,2,FALSE) -> #N/A | H81: =VLOOKUP("*" & F81 & "*",$B$71:$C$77,2,FALSE) -> Miow
A83: * | B83: SUPPLEMENTARY INFORMATION
A85: * | B85: Vlookup, Hlookup, Xlookup, Index Match
B87: Vlookup's biggest strength is that it's easier to teach and practice with than the other methods!
B88: Use Hlookup to lookup values across columns instead of across rows.
B89: If you have a recent version of Excel, use Xlookup instead of Vlookup. It has the benefit of handling errors without nesting inside an IFERROR.
B90: If you are very confident with Excel, or need efficiency (such as when working with hundreds of thousands of rows of data), look into Index Match
A92: * | B92: Table of animals and the sounds that they make | E92: Vlookup, Xlookup, and Index Match examples
B93: Animals | C93: Sounds | E93: Formula | F93: Active formula | G93: Formula text
B94: Cat | C94: Miow | E94: Vlookup | F94: =VLOOKUP(C102,$B$94:$C$100,2,FALSE) -> Miow | G94: =VLOOKUP(C102,$B$94:$C$100,2,FALSE)
B95: Giraffe | C95: ??? | E95: Xlookup | F95: =_xlfn.XLOOKUP(C102,$B$94:$B$100,$C$94:$C$100,"???",2) -> Miow | G95: =XLOOKUP(C102,$B$94:$B$100,$C$94:$C$100,"???",0)
B96: Cricket | C96: Cricket cricket | E96: Index Match | F96: =INDEX($B$94:$C$100,MATCH(C102,$B$94:$B$100,0),2) -> Miow | G96: =INDEX($B$94:$C$100,MATCH(C102,$B$94:$B$100,0),2)
B97: Cow | C97: Mooo
B98: Pig | C98: Oink oink | E98: Element | F98: Example
B99: Duck | C99: Quack quack | E99: Value to lookup | F99: C102
B100: Dog | C100: Woof | E100: Animal sounds table | F100: $B$94:$C$100
E101: Animal column | F101: $B$94:$B$100
B102: Animal to look up | C102: Cat | E102: Sound column | F102: $C$94:$C$100 or 2
E103: Exact match | F103: FALSE or 0

Sheet C3 Exercise
A1: * | B1: Main Menu | C1: Instructions
A3: * | B3: VLOOKUP EXERCISE
B4: You've been compiling a list of famous people, the city and country they come from, and how the average temperature of that city had an impact on their career.
B5: However, you're a busy person! You can't be expected to type up the country and the temperature each time you put in the name of the city.
B6: So to speed things up here, use Vlookup to find the appropriate country in column H, and the status/temperature in column I.
A8: * | B8: Table with values to look up | F8: Your table with values to find
B9: City | C9: Country | D9: Status | F9: Celebrities | G9: City of origin | H9: Look up the country | I9: Look up the status
B10: Moncton | C10: Canada | D10: Cold and wet | F10: Atwood, Margaret | G10: Ottawa
B11: Ottawa | C11: Canada | D11: Cold | F11: Bastarache, Michel | G11: Moncton
B12: Winnipeg | C12: Canada | D12: Colder | F12: Claus, Santa | G12: Christmas Village
B13: Honolulu | C13: Hawaii | D13: Nice and warm | F13: Fox, Terry | G13: Winnipeg
B14: Christmas Village | C14: North Pole | D14: Magical | F14: Kay, Guy Gavriel | G14: Winnipeg
B15: Las Vegas | C15: United States | D15: Too hot | F15: Keith, Alexander | G15: Halifax
B16: Halifax | C16: Canada | D16: So much rain | F16: Mars, Bruno | G16: Honolulu
F17: McLachlan, Sarah | G17: Halifax
F18: Morissette, Alanis | G18: Ottawa
F19: Obama, Barack | G19: Honolulu
F20: Roy, Gabrielle | G20: Winnipeg
F21: Sinatra, Frank | G21: Las Vegas

Sheet C4 Instructions
A1: * | B1: Main Menu | C1: Exercise
C3: C4 CSE FORMULAS
C5: What are we doing here?
C6: Depending on your version of Excel, CSE formulas are top secret formulas
C7: that you have to do a special key stroke in order to activate.
C8: Or they're weird formulas that you create with the normal = method.
C9: Either way, they are based on arrays, which I'm too scared to explain much.
C11: This is amazing! What if I want to do more?
C12: Google "CSE formulas Excel". There's tons of explanations out there!
C14: How do I get started again?
C15: This example is ready to go, just keep reading!
C16: Once you think you understand, go do the hardest exercise yet!
A19: * | B19: INSTRUCTIONS
B20: Before going further, let's figure out if your version of Excel requires you to use a special key stroke to activate CSE formulas.
B21: Look here ----------------> | C21: {=SUM($C$44:$C$47*$D$44:$D$47)} -> 36.61
B23: If you see "$4.00" or if you click on C21 and see curly brackets {} in the formula bar,
B24: you must type in your formula, then press Ctrl-Shift-Enter to activate your CSE formulas.
B25: You will notice curly brackes appear in the formula bar. You can't make a CSE formula work correctly by typing in the curly brackets manually.
B27: If you see "$36.41", you can use the normal = method to create CSE formulas. You won't see curly brackets in the formula bar.
B28: Doing Ctrl-Shift-Enter should also work and will make curly brackets appear in the formula bar. Don't type these brackets in manually.
B29: But I recommend just entering formulas using = as normal.
B31: In either case, the "*" symbol between CSE instances tends to work as an "AND".
B32: The "+" symbol between CSE instances tends to work as an "OR" but you must be ready to throw down some "If" in your formula.
B34: Because most people are familiar with the SUM formula, I used these for my examples, but among other tricks,
B35: CSE formulas can be used to add "IF" logic to formulas that don't already have that component. See section 2_5 for more on IF formulas.
B36: In the first example, we're getting the SUM function to give us the grand total of the sum of quantities multiplied by unit price.
B37: In the second example, we're getting the number of vehicles that are red cars. Change the criteria and you should still get the right result.
B38: In more recent versions of excel, we could have used =sumIFs to find red cars, but not red or yellow vehicles.
A40: * | B40: Simple CSE formula (no multiplying or adding arrays)
A42: * | B42: Grocerly list with quantities and unit prices
B43: Grocery list | C43: Quantities | D43: Unit Price
B44: Ground beef | C44: 2 | D44: 10.25
B45: Potatoes | C45: 16 | D45: 0.25
B46: Maple Syrup | C46: 1 | D46: 8.95
B47: Apples | C47: 4 | D47: 0.79
A49: * | B49: CSE formulas
B50: Formula version | C50: Active formula | D50: Formula text
B51: Entered normally | C51: {=SUM($C$44:$C$47*$D$44:$D$47)} -> 36.61 | D51: =SUM($C$44:$C$47*$D$44:$D$47)
B52: Ctrl-Shift-Enter | C52: {=SUM($C$44:$C$47*$D$44:$D$47)} -> 36.61 | D52: {=SUM($C$44:$C$47*$D$44:$D$47)}
A54: * | B54: Complex CSE formula (multiplying arrays)
A56: * | B56: Vehicle list with color, vehicle, and total count | F56: Criteria
B57: Color | C57: Vehicle | D57: Total | F57: Color to add
B58: Red | C58: Trucks | D58: 2 | F58: Red
B59: Red | C59: Cars | D59: 3
B60: Yellow | C60: Cars | D60: 1 | F60: Vehicle to add
B61: Blue | C61: Bicycles | D61: 6 | F61: Cars
B62: Yellow | C62: Bicycles | D62: 2
B63: Red | C63: Cars | D63: 4
A65: * | B65: CSE formulas
B66: Formula version | C66: Active formula | D66: Formula text
B67: Red car [normal] | C67: {=SUM(($B$58:$B$63=F$58)*($C$58:$C$63=F$61)*($D$58:$D$63))} -> 7 | D67: =SUM(($B$58:$B$63=F58)*($C$58:$C$63=F61)*($D$58:$D$63))
B68: Red car [CSE] | C68: {=SUM(($B$58:$B$63=F$58)*($C$58:$C$63=F$61)*($D$58:$D$63))} -> 7 | D68: {=SUM(($B$58:$B$63=F58)*($C$58:$C$63=F61)*($D$58:$D$63))}
A70: * | B70: Complex CSE formula (adding arrays)
A72: * | B72: Vehicle list with color, vehicle, and total count | F72: Criteria
B73: Color | C73: Vehicle | D73: Total | F73: Color to add
B74: Red | C74: Trucks | D74: 2 | F74: Red
B75: Red | C75: Cars | D75: 3
B76: Yellow | C76: Cars | D76: 1 | F76: Other color to add
B77: Blue | C77: Bicycles | D77: 6 | F77: Yellow
B78: Yellow | C78: Bicycles | D78: 2
B79: Red | C79: Cars | D79: 4
A81: * | B81: CSE formulas
B82: Formula version | C82: Active formula | D82: Formula text
B83: Red or yellow [normal] | C83: {=SUM((($B$74:$B$79=F$74)+($B$74:$B$79=F$77))*($D$74:$D$79))} -> 12 | D83: =SUM((($B$74:$B$79=F$74)+($B$74:$B$79=F$77))*($D$74:$D$79))
B84: Red or yellow [CSE] | C84: {=SUM((($B$74:$B$79=F$74)+($B$74:$B$79=F$77))*($D$74:$D$79))} -> 12 | D84: {=SUM((($B$74:$B$79=F$74)+($B$74:$B$79=F$77))*($D$74:$D$79))}

Sheet C4 Exercise
A1: * | B1: Main Menu | C1: Instructions
A3: * | B3: CSE FORMULA EXERCISE
B4: There's no "PercentileIf" function in Excel. Let's create our own in column G!
B5: This is a REALLY hard exercise, so hopefully you'll be able to do it.
B6: You DO need to use "If" in order to get it to work, so you might want to read Excel's help about the If function or look at section 2_5.
B7: Remember that if you don't have the latest version of Excel, you will need to use Control-Shift-Enter to activate the formula.
B9: The Percentile.Inc function takes two arguments, it wants to know where the data is, and then it wants "k" which is a number between 0 and 1.
B10: If you put k = 0, it will give you the lowest value found. If you put k = 1, it will give you the biggest value found.
B12: Adapt the Percentile function so that it will give you the result for the city of your choice.
B13: The city is in F19 and the centile/k is in G19. Test by checking the lowest (0) and highest values (1) for each city.
B15: If you can't do it, I've hidden the answer in cell H43. But first, try a simple version of the percentile function and then add complexity!
A17: * | B17: Table of precipitation by city by date | F17: Find the percentile for a city of your choice
B18: Date | C18: City | D18: Precipitation (mm) | F18: City | G18: Centile K | H18: CSE Percentile Formula
B19: April 21 | C19: Ottawa | D19: 46 | F19: Ottawa | G19: 1
C20: Vancouver | D20: 23
C21: Moncton | D21: 2
C22: Montreal | D22: 42
C23: Fredericton | D23: 0
B24: April 22 | C24: Ottawa | D24: 18
C25: Vancouver | D25: 25
C26: Moncton | D26: 5
C27: Montreal | D27: 16
C28: Fredericton | D28: 0
B29: April 23 | C29: Ottawa | D29: 55
C30: Vancouver | D30: 120
C31: Moncton | D31: 8
C32: Montreal | D32: 44
C33: Fredericton | D33: 5
B34: April 24 | C34: Ottawa | D34: 0
C35: Vancouver | D35: 56
C36: Moncton | D36: 0
C37: Montreal | D37: 0
C38: Fredericton | D38: 0
B39: April 25 | C39: Ottawa | D39: 20
C40: Vancouver | D40: 86
C41: Moncton | D41: 4
C42: Montreal | D42: 18
C43: Fredericton | D43: 4 | H43: =PERCENTILE.INC(IF($C$18:$C$42=F18,$D$18:$D$42),G18)

Sheet 2021 CSD
A1: Province | B1: CD | C1: SUBDIV | D1: SUBDIV Name | E1: Tot Pop 2021 | F1: Low Income 0 to 17 | G1: Low Income 18 to 64 | H1: Low income 65 years and more | I1: Owner | J1: Renter
A2: 12 | B2: 1 | C2: 1 | D2: Barrington | E2: 6523 | F2: 1030 | G2: 3840 | H2: 1580 | I2: 2535 | J2: 485 | L2: Main Menu
A3: 12 | B3: 1 | C3: 4 | D3: Clark's Harbour | E3: 725 | F3: 130 | G3: 445 | H3: 150 | I3: 280 | J3: 80
A4: 12 | B4: 1 | C4: 6 | D4: Shelburne | E4: 4336 | F4: 630 | G4: 2440 | H4: 1195 | I4: 1725 | J4: 340 | L4: A1 | M4: Paste as values
A5: 12 | B5: 1 | C5: 8 | D5: Shelburne | E5: 1644 | F5: 310 | G5: 875 | H5: 440 | I5: 525 | J5: 265 | L5: A4 | M5: Remove duplicates
A6: 12 | B6: 1 | C6: 9 | D6: Lockeport | E6: 476 | F6: 55 | G6: 210 | H6: 175 | I6: 180 | J6: 55 | L6: B4 | M6: SumIf and SumIfs
A7: 12 | B7: 2 | C7: 1 | D7: Argyle | E7: 7870 | F7: 1230 | G7: 4520 | H7: 2040 | I7: 3155 | J7: 300 | L7: C1 | M7: Concatenation
A8: 12 | B8: 2 | C8: 4 | D8: Yarmouth | E8: 10067 | F8: 1680 | G8: 5775 | H8: 2490 | I8: 3865 | J8: 565 | L8: C2 | M8: Left, right, mid, find
A9: 12 | B9: 2 | C9: 6 | D9: Yarmouth | E9: 6829 | F9: 1175 | G9: 3745 | H9: 1700 | I9: 1430 | J9: 1830
A10: 12 | B10: 2 | C10: 40 | D10: Yarmouth 33 | E10: 181 | F10: x | G10: x | H10: x | I10: 0 | J10: 0
A11: 12 | B11: 3 | C11: 1 | D11: Clare | E11: 7678 | F11: 950 | G11: 4315 | H11: 2250 | I11: 3140 | J11: 475
A12: 12 | B12: 3 | C12: 4 | D12: Digby | E12: 7242 | F12: 1090 | G12: 4035 | H12: 2105 | I12: 2775 | J12: 645
A13: 12 | B13: 3 | C13: 6 | D13: Digby | E13: 2001 | F13: 280 | G13: 1030 | H13: 585 | I13: 420 | J13: 610
A14: 12 | B14: 3 | C14: 9 | D14: Bear River (Part) 6 | E14: 141 | F14: x | G14: x | H14: x | I14: 0 | J14: 0
A15: 12 | B15: 4 | C15: 1 | D15: Medway River 11 | E15: 15 | F15: x | G15: x | H15: x | I15: x | J15: x
A16: 12 | B16: 4 | C16: 9 | D16: Ponhook Lake 10 | E16: 15 | F16: x | G16: x | H16: x | I16: x | J16: x
A17: 12 | B17: 4 | C17: 10 | D17: Queens | E17: 10422 | F17: 1400 | G17: 5705 | H17: 3160 | I17: 4095 | J17: 885
A18: 12 | B18: 4 | C18: 15 | D18: Wildcat 12 | E18: 49 | F18: x | G18: x | H18: x | I18: 0 | J18: 0
A19: 12 | B19: 5 | C19: 1 | D19: Annapolis, Subd. D | E19: 3049 | F19: 515 | G19: 1785 | H19: 745 | I19: 1205 | J19: 165
A20: 12 | B20: 5 | C20: 2 | D20: Bear River (Part) 6 | E20: 0 | F20: x | G20: x | H20: x | I20: x | J20: x
A21: 12 | B21: 5 | C21: 4 | D21: Annapolis, Subd. A | E21: 5980 | F21: 820 | G21: 3160 | H21: 1945 | I21: 2535 | J21: 340
A22: 12 | B22: 5 | C22: 6 | D22: Bear River 6B | E22: 15 | F22: x | G22: x | H22: x | I22: x | J22: x
A23: 12 | B23: 5 | C23: 8 | D23: Annapolis Royal | E23: 530 | F23: 30 | G23: 225 | H23: 265 | I23: 180 | J23: 145
A24: 12 | B24: 5 | C24: 9 | D24: Annapolis, Subd. B | E24: 4587 | F24: 705 | G24: 2470 | H24: 1245 | I24: 1555 | J24: 500
A25: 12 | B25: 5 | C25: 14 | D25: Annapolis, Subd. C | E25: 5218 | F25: 890 | G25: 3100 | H25: 1190 | I25: 1885 | J25: 420
A26: 12 | B26: 5 | C26: 16 | D26: Middleton | E26: 1873 | F26: 310 | G26: 995 | H26: 510 | I26: 425 | J26: 500
A27: 12 | B27: 6 | C27: 1 | D27: Lunenburg | E27: 25545 | F27: 3730 | G27: 14465 | H27: 7200 | I27: 10340 | J27: 1165
A28: 12 | B28: 6 | C28: 4 | D28: Bridgewater | E28: 8790 | F28: 1255 | G28: 4855 | H28: 2380 | I28: 2470 | J28: 1790
A29: 12 | B29: 6 | C29: 6 | D29: Lunenburg | E29: 2396 | F29: 325 | G29: 1160 | H29: 715 | I29: 690 | J29: 405
A30: 12 | B30: 6 | C30: 8 | D30: Mahone Bay | E30: 1064 | F30: 145 | G30: 480 | H30: 375 | I30: 355 | J30: 170
A31: 12 | B31: 6 | C31: 9 | D31: Chester | E31: 10693 | F31: 1485 | G31: 5905 | H31: 3170 | I31: 4205 | J31: 830
A32: 12 | B32: 6 | C32: 11 | D32: Gold River 21 | E32: 81 | F32: x | G32: x | H32: x | I32: 0 | J32: 0
A33: 12 | B33: 6 | C33: 14 | D33: Pennal 19 | E33: 30 | F33: x | G33: x | H33: x | I33: x | J33: x
A34: 12 | B34: 6 | C34: 16 | D34: New Ross 20 | E34: 0 | F34: x | G34: x | H34: x | I34: x | J34: x
A35: 12 | B35: 7 | C35: 1 | D35: Kings, Subd. A | E35: 22355 | F35: 4345 | G35: 12935 | H35: 4740 | I35: 6970 | J35: 2490
A36: 12 | B36: 7 | C36: 2 | D36: Annapolis Valley First Nation | E36: 743 | F36: 160 | G36: 440 | H36: 145 | I36: 195 | J36: 75
A37: 12 | B37: 7 | C37: 4 | D37: Berwick | E37: 2455 | F37: 350 | G37: 1190 | H37: 645 | I37: 650 | J37: 390
A38: 12 | B38: 7 | C38: 11 | D38: Kings, Subd. C | E38: 8348 | F38: 1395 | G38: 4915 | H38: 2015 | I38: 2485 | J38: 1305
A39: 12 | B39: 7 | C39: 12 | D39: Kentville | E39: 6630 | F39: 1125 | G39: 3835 | H39: 1400 | I39: 1635 | J39: 1325
A40: 12 | B40: 7 | C40: 16 | D40: Kings, Subd. B | E40: 11951 | F40: 2165 | G40: 7120 | H40: 2625 | I40: 3845 | J40: 1340
A41: 12 | B41: 7 | C41: 21 | D41: Kings, Subd. D | E41: 5264 | F41: 795 | G41: 3035 | H41: 1380 | I41: 1950 | J41: 345
A42: 12 | B42: 7 | C42: 24 | D42: Wolfville | E42: 5057 | F42: 515 | G42: 3110 | H42: 1230 | I42: 940 | J42: 1500
A43: 12 | B43: 7 | C43: 27 | D43: Glooscap 35 | E43: 111 | F43: x | G43: x | H43: x | I43: 10 | J43: 0
A44: 12 | B44: 8 | C44: 3 | D44: West Hants | E44: 19509 | F44: 3445 | G44: 11195 | H44: 4485 | I44: 6660 | J44: 1715
A45: 12 | B45: 8 | C45: 8 | D45: East Hants | E45: 22892 | F45: 4525 | G45: 14135 | H45: 4200 | I45: 7625 | J45: 1760
A46: 12 | B46: 8 | C46: 14 | D46: Indian Brook 14 | E46: 2739 | F46: 680 | G46: 1655 | H46: 405 | I46: 635 | J46: 90
A47: 12 | B47: 9 | C47: 19 | D47: Cole Harbour 30 | E47: 208 | F47: x | G47: x | H47: x | I47: 10 | J47: 110
A48: 12 | B48: 9 | C48: 34 | D48: Halifax | E48: 439819 | F48: 77805 | G48: 284175 | H48: 73310 | I48: 109540 | J48: 80965
A49: 12 | B49: 9 | C49: 37 | D49: Beaver Lake 17 | E49: 20 | F49: x | G49: x | H49: x | I49: x | J49: x
A50: 12 | B50: 9 | C50: 38 | D50: Sheet Harbour 36 | E50: 10 | F50: x | G50: x | H50: x | I50: x | J50: x
A51: 12 | B51: 9 | C51: 800 | D51: Wallace Hills 14A | E51: 15 | F51: x | G51: x | H51: x | I51: x | J51: x
A52: 12 | B52: 10 | C52: 1 | D52: Colchester, Subd. C | E52: 12476 | F52: 2340 | G52: 7430 | H52: 2650 | I52: 4325 | J52: 995
A53: 12 | B53: 10 | C53: 2 | D53: Stewiacke | E53: 1557 | F53: 290 | G53: 885 | H53: 375 | I53: 440 | J53: 275
A54: 12 | B54: 10 | C54: 3 | D54: Millbrook 27 | E54: 921 | F54: 250 | G54: 545 | H54: 75 | I54: 50 | J54: 10
A55: 12 | B55: 10 | C55: 6 | D55: Truro | E55: 12954 | F55: 1985 | G55: 7375 | H55: 3060 | I55: 2700 | J55: 3650
A56: 12 | B56: 10 | C56: 8 | D56: Colchester, Subd. B | E56: 19806 | F56: 3520 | G56: 11380 | H56: 4715 | I56: 6770 | J56: 1930
A57: 12 | B57: 10 | C57: 12 | D57: Colchester, Subd. A | E57: 3762 | F57: 625 | G57: 2115 | H57: 955 | I57: 1465 | J57: 180
A58: 12 | B58: 11 | C58: 1 | D58: Cumberland, Subd. A | E58: 3201 | F58: 440 | G58: 1665 | H58: 1050 | I58: 1295 | J58: 290
A59: 12 | B59: 11 | C59: 6 | D59: Cumberland, Subd. B | E59: 6786 | F59: 1010 | G59: 3600 | H59: 1740 | I59: 2455 | J59: 535
A60: 12 | B60: 11 | C60: 9 | D60: Cumberland, Subd. C | E60: 5694 | F60: 940 | G60: 3120 | H60: 1595 | I60: 2220 | J60: 305
A61: 12 | B61: 11 | C61: 11 | D61: Amherst | E61: 9404 | F61: 1660 | G61: 5245 | H61: 2340 | I61: 2565 | J61: 1915
A62: 12 | B62: 11 | C62: 12 | D62: Oxford | E62: 1170 | F62: 235 | G62: 660 | H62: 250 | I62: 355 | J62: 180
A63: 12 | B63: 11 | C63: 14 | D63: Cumberland, Subd. D | E63: 4283 | F63: 510 | G63: 2205 | H63: 1425 | I63: 1760 | J63: 255
... A72: 12 | B72: 12 | C72: 19 | D72: Fisher's Grant 24 | E72: 449 | F72: 115 | G72: 305 | H72: 30 | I72: 15 | J72: 10
A73: 12 | B73: 12 | C73: 23 | D73: Merigomish Harbour 31 | E73: 0 | F73: x | G73: x | H73: x | I73: x | J73: x
A74: 12 | B74: 13 | C74: 1 | D74: St. Mary's | E74: 2161 | F74: 285 | G74: 1150 | H74: 690 | I74: 945 | J74: 105
A75: 12 | B75: 13 | C75: 4 | D75: Guysborough | E75: 4585 | F75: 615 | G75: 2345 | H75: 1555 | I75: 1925 | J75: 295
A76: 12 | B76: 13 | C76: 8 | D76: Mulgrave | E76: 627 | F76: 95 | G76: 345 | H76: 190 | I76: 245 | J76: 50
A77: 12 | B77: 14 | C77: 1 | D77: Antigonish, Subd. A | E77: 8963 | F77: 1750 | G77: 4935 | H77: 2185 | I77: 3030 | J77: 745
A78: 12 | B78: 14 | C78: 2 | D78: Antigonish | E78: 4656 | F78: 660 | G78: 2795 | H78: 1000 | I78: 955 | J78: 1250
A79: 12 | B79: 14 | C79: 6 | D79: Antigonish, Subd. B | E79: 6138 | F79: 1145 | G79: 3605 | H79: 1380 | I79: 2390 | J79: 205
A80: 12 | B80: 14 | C80: 10 | D80: Paqtnkek-Niktuek No. 23 | E80: 372 | F80: 130 | G80: 225 | H80: 15 | I80: 10 | J80: 15
A81: 12 | B81: 15 | C81: 1 | D81: Inverness, Subd. C | E81: 3167 | F81: 445 | G81: 1705 | H81: 960 | I81: 1310 | J81: 120
A82: 12 | B82: 15 | C82: 2 | D82: Port Hawkesbury | E82: 3210 | F82: 550 | G82: 1865 | H82: 725 | I82: 860 | J82: 550
A83: 12 | B83: 15 | C83: 5 | D83: Malagawatch 4 | E83: 20 | F83: x | G83: x | H83: x | I83: x | J83: x
A84: 12 | B84: 15 | C84: 6 | D84: Inverness, Subd. B | E84: 4865 | F84: 795 | G84: 2480 | H84: 1470 | I84: 1745 | J84: 420
A85: 12 | B85: 15 | C85: 8 | D85: Whycocomagh 2 | E85: 877 | F85: 325 | G85: 505 | H85: 40 | I85: 40 | J85: 10
A86: 12 | B86: 15 | C86: 11 | D86: Inverness, Subd. A | E86: 5207 | F86: 730 | G86: 2680 | H86: 1665 | I86: 2030 | J86: 365
A87: 12 | B87: 16 | C87: 1 | D87: Richmond, Subd. C | E87: 3136 | F87: 445 | G87: 1720 | H87: 940 | I87: 1210 | J87: 245
A88: 12 | B88: 16 | C88: 6 | D88: Richmond, Subd. A | E88: 3763 | F88: 545 | G88: 1975 | H88: 1160 | I88: 1360 | J88: 370
A89: 12 | B89: 16 | C89: 11 | D89: Richmond, Subd. B | E89: 1610 | F89: 165 | G89: 865 | H89: 585 | I89: 695 | J89: 85
A90: 12 | B90: 16 | C90: 14 | D90: Chapel Island 5 | E90: 405 | F90: 130 | G90: 250 | H90: 25 | I90: 15 | J90: 0
A91: 12 | B91: 17 | C91: 8 | D91: Membertou 28B | E91: 1103 | F91: 355 | G91: 665 | H91: 90 | I91: 50 | J91: 25
A92: 12 | B92: 17 | C92: 20 | D92: Eskasoni 3 | E92: 3521 | F92: 1300 | G92: 1995 | H92: 225 | I92: 175 | J92: 130
A93: 12 | B93: 17 | C93: 30 | D93: Cape Breton | E93: 93694 | F93: 14450 | G93: 53780 | H93: 23790 | I93: 30100 | J93: 12215
A94: 12 | B94: 18 | C94: 1 | D94: Victoria, Subd. B | E94: 4077 | F94: 585 | G94: 2150 | H94: 1255 | I94: 1620 | J94: 240
A95: 12 | B95: 18 | C95: 3 | D95: Wagmatcook 1 | E95: 691 | F95: 270 | G95: 360 | H95: 65 | I95: 30 | J95: 0
A96: 12 | B96: 18 | C96: 6 | D96: Victoria, Subd. A | E96: 2673 | F96: 415 | G96: 1495 | H96: 720 | I96: 1110 | J96: 110

Sheet ContactInfo
E1: Main Menu
E4: Need more help?
E5: You could try contacting me! I'm always happy to help with Excel questions.
E7: As of 2026 you can reach me:
D8: By email | E8: Julie.Marcoux@dal.ca
E9: (On research leave from July 2026 to June 2027)
E11: More self-teaching Excel files?
E12: http://dal.ca.libguides.com/data/excel
